[{"name":"Keyboard","actions":{"535":{"id":"DUP_ALL","title":"Repeat the last note, including non-printable characters","icon":"copy_all","printable":false,"separator":true,"breaking":false,"modifier":false},"536":{"id":"DUP","variant":"left","title":"Repeat Last Note","icon":"markdown_copy","description":"In character entry, it repeats your last input.\nIn chorded entry, it is used for words with repeating letters.\n","printable":true,"separator":false,"breaking":false,"modifier":false},"533":{"id":"DUP_RIGHT","variant":"right","title":"Repeat Last Note","icon":"markdown_copy","description":"In character entry, it repeats your last input.\nIn chorded entry, it is used for words with repeating letters.\n","variantOf":536,"printable":true,"separator":false,"breaking":false,"modifier":false},"335":{"id":"ARROW_RT","name":"RIGHT_ARROW","keyCode":"ArrowRight","title":"Keyboard Right Arrow","icon":"keyboard_arrow_right","breaking":true,"printable":false,"separator":true,"modifier":false},"336":{"id":"ARROW_LF","name":"LEFT_ARROW","keyCode":"ArrowLeft","title":"Keyboard Left Arrow","icon":"keyboard_arrow_left","breaking":true,"printable":false,"separator":true,"modifier":false},"337":{"id":"ARROW_DN","name":"DOWN_ARROW","keyCode":"ArrowDown","title":"Keyboard Down Arrow","icon":"keyboard_arrow_down","breaking":true,"printable":false,"separator":true,"modifier":false},"338":{"id":"ARROW_UP","name":"UP_ARROW","keyCode":"ArrowUp","title":"Keyboard Up Arrow","icon":"keyboard_arrow_up","breaking":true,"printable":false,"separator":true,"modifier":false},"296":{"id":"ENTER","name":"RETURN","keyCode":"Enter","title":"Keyboard Return (US English)","icon":"keyboard_return","separator":true,"printable":true,"breaking":false,"modifier":false},"298":{"id":"BKSP","name":"BACKSPACE","keyCode":"Backspace","title":"Keyboard Backspace (US English)","icon":"backspace","printable":false,"separator":true,"breaking":false,"modifier":false},"127":{"id":"DEL","name":"DELETE","keyCode":"Delete","title":"Delete","breaking":true,"printable":false,"alias":[332],"separator":true,"modifier":false},"330":{"id":"HOME","keyCode":"Home","title":"Keyboard Home","breaking":true,"printable":false,"separator":true,"modifier":false},"331":{"id":"PGUP","name":"PAGE_UP","keyCode":"PageUp","title":"Keyboard Page Up","breaking":true,"printable":false,"separator":true,"modifier":false},"333":{"id":"END","keyCode":"End","title":"Keyboard End","breaking":true,"printable":false,"separator":true,"modifier":false},"334":{"id":"PGDN","name":"PAGE_DOWN","keyCode":"PageDown","title":"Keyboard Page Down","breaking":true,"printable":false,"separator":true,"modifier":false},"297":{"id":"ESC","name":"ESCAPE","keyCode":"Escape","title":"Keyboard Escape (US English)","printable":false,"breaking":true,"separator":true,"modifier":false},"299":{"id":"TAB","keyCode":"Tab","title":"Keyboard Tab (US English)","icon":"keyboard_tab","separator":true,"printable":true,"breaking":false,"modifier":false}}},{"name":"Modifiers","actions":{"512":{"id":"LEFT_CTRL","name":"LEFT_CONTROL","display":"CTRL","title":"Control Modifier","keyCode":"ControlLeft","variant":"left","printable":false,"breaking":true,"separator":true,"modifier":false},"513":{"id":"LEFT_SHIFT","title":"Shift Modifier","keyCode":"ShiftLeft","variant":"left","icon":"shift","printable":false,"separator":false,"modifier":true,"breaking":false},"514":{"id":"LEFT_ALT","display":"ALT","title":"Alt Modifier","keyCode":"AltLeft","variant":"left","printable":false,"breaking":true,"separator":true,"modifier":false},"515":{"id":"LEFT_GUI","title":"GUI/Windows/Super Modifier","keyCode":"MetaLeft","icon":"apps","variant":"left","printable":false,"breaking":true,"separator":true,"modifier":false},"516":{"id":"RIGHT_CTRL","name":"RIGHT_CONTROL","display":"CTRL","title":"Control Modifier","keyCode":"ControlRight","variant":"right","printable":false,"breaking":true,"variationOf":512,"separator":true,"modifier":false},"517":{"id":"RIGHT_SHIFT","title":"Shift Modifier","keyCode":"ShiftRight","variant":"right","icon":"shift","printable":false,"separator":false,"modifier":true,"variationOf":513,"breaking":false},"518":{"id":"RIGHT_ALT","display":"ALT","title":"Alt Modifier","keyCode":"AltRight","variant":"right","printable":false,"breaking":false,"variationOf":514,"separator":false,"modifier":true},"519":{"id":"RIGHT_GUI","title":"GUI/Windows/Super Modifier","keyCode":"MetaRight","icon":"apps","variant":"right","printable":false,"breaking":true,"variationOf":515,"separator":true,"modifier":false},"313":{"id":"CAPSLOCK","name":"CAPS_LOCK","keyCode":"CapsLock","title":"Caps Lock","icon":"shift_lock","printable":false,"separator":true,"breaking":false,"modifier":false},"650":{"id":"PROFILE_A","display":"Ax","title":"Profile A","printable":false,"breaking":true,"separator":true,"modifier":false},"651":{"id":"PROFILE_B","display":"Bx","title":"Profile B","printable":false,"breaking":true,"separator":true,"modifier":false},"652":{"id":"PROFILE_C","display":"Cx","title":"Profile C","printable":false,"breaking":true,"separator":true,"modifier":false},"540":{"id":"AMBILEFT","name":"MIRROR_R_ONTO_L","title":"Ambidextrous Throwover","icon":"switch_left","variant":"left","description":"Entry mode designed for one-handed typing.\nCharacters from the opposite hand are mirrored to the hand which activates this feature.\n","printable":false,"separator":false,"modifier":true,"breaking":false},"542":{"id":"AMBIRIGHT","name":"MIRROR_L_ONTO_R","title":"Ambidextrous Throwover","icon":"switch_right","variant":"right","description":"Entry mode designed for one-handed typing.\nCharacters from the opposite hand are mirrored to the hand which activates this feature.\n","printable":false,"separator":false,"modifier":true,"variantOf":540,"breaking":false},"548":{"id":"KM_1_L","name":"PRIMARY_KEYMAP_L","title":"Primary Layer","icon":"counter_1","variant":"left","description":"Can be used as a toggle if you assign a different key to its target layer.\n","printable":false,"sparator":false,"modifier":true,"separator":true,"breaking":false},"549":{"id":"KM_1_R","name":"PRIMARY_KEYMAP_R","title":"Primary Layer","icon":"counter_1","variant":"right","description":"Can be used as a toggle if you assign a different key to its target layer.\n","printable":false,"sparator":false,"modifier":true,"variantOf":548,"separator":true,"breaking":false},"550":{"id":"KM_2_L","name":"SECONDARY_KEYMAP_L","title":"Numeric Layer","icon":"counter_2","variant":"left","description":"Can be used as a toggle if you assign a different key to its target layer.\n","printable":false,"separator":false,"modifier":true,"breaking":false},"551":{"id":"KM_2_R","name":"SECONDARY_KEYMAP_R","title":"Numeric Layer","icon":"counter_2","variant":"right","description":"Can be used as a toggle if you assign a different key to its target layer.\n","printable":false,"separator":false,"modifier":true,"variantOf":550,"breaking":false},"552":{"id":"KM_3_L","name":"TERTIARY_KEYMAP_L","title":"Function Layer","icon":"counter_3","variant":"left","description":"Can be used as a toggle if you assign a different key to its target layer.\n","printable":false,"separator":false,"modifier":true,"breaking":false},"553":{"id":"KM_3_R","name":"TERTIARY_KEYMAP_R","title":"Function Layer","icon":"counter_3","variant":"right","description":"Can be used as a toggle if you assign a different key to its target layer.\n","printable":false,"separator":false,"modifier":true,"variationOf":552,"breaking":false},"554":{"id":"KM_4_L","name":"QUATERNARY_KEYMAP_L","title":"Flag Layer","icon":"counter_4","variant":"left","description":"Can be used as a toggle if you assign a different key to its target layer.\n","printable":false,"separator":false,"modifier":true,"breaking":false},"555":{"id":"KM_4_R","name":"QUATERNARY_KEYMAP_R","title":"Flag Layer","icon":"counter_4","variant":"right","description":"Can be used as a toggle if you assign a different key to its target layer.\n","printable":false,"separator":false,"modifier":true,"variationOf":554,"breaking":false}}},{"name":"F-Keys","actions":{"314":{"id":"F1","keyCode":"F1","title":"Keyboard F1","printable":false,"separator":true,"breaking":false,"modifier":false},"315":{"id":"F2","keyCode":"F2","title":"Keyboard F2","printable":false,"separator":true,"breaking":false,"modifier":false},"316":{"id":"F3","keyCode":"F3","title":"Keyboard F3","printable":false,"separator":true,"breaking":false,"modifier":false},"317":{"id":"F4","keyCode":"F4","title":"Keyboard F4","printable":false,"separator":true,"breaking":false,"modifier":false},"318":{"id":"F5","keyCode":"F5","title":"Keyboard F5","printable":false,"separator":true,"breaking":false,"modifier":false},"319":{"id":"F6","keyCode":"F6","title":"Keyboard F6","printable":false,"separator":true,"breaking":false,"modifier":false},"320":{"id":"F7","keyCode":"F7","title":"Keyboard F7","printable":false,"separator":true,"breaking":false,"modifier":false},"321":{"id":"F8","keyCode":"F8","title":"Keyboard F8","printable":false,"separator":true,"breaking":false,"modifier":false},"322":{"id":"F9","keyCode":"F9","title":"Keyboard F9","printable":false,"separator":true,"breaking":false,"modifier":false},"323":{"id":"F10","keyCode":"F10","title":"Keyboard F10","printable":false,"separator":true,"breaking":false,"modifier":false},"324":{"id":"F11","keyCode":"F11","title":"Keyboard F11","printable":false,"separator":true,"breaking":false,"modifier":false},"325":{"id":"F12","keyCode":"F12","title":"Keyboard F12","printable":false,"separator":true,"breaking":false,"modifier":false},"360":{"id":"F13","title":"Keyboard F13","description":"Only officially supported by Mac","printable":false,"separator":true,"breaking":false,"modifier":false},"361":{"id":"F14","title":"Keyboard F14","description":"Only officially supported by Mac","printable":false,"separator":true,"breaking":false,"modifier":false},"362":{"id":"F15","title":"Keyboard F15","description":"Only officially supported by Mac","printable":false,"separator":true,"breaking":false,"modifier":false},"363":{"id":"F16","title":"Keyboard F16","description":"Only officially supported by Mac","printable":false,"separator":true,"breaking":false,"modifier":false},"364":{"id":"F17","title":"Keyboard F17","description":"Not required to be supported by any OS","printable":false,"separator":true,"breaking":false,"modifier":false},"365":{"id":"F18","title":"Keyboard F18","description":"Not required to be supported by any OS","printable":false,"separator":true,"breaking":false,"modifier":false},"366":{"id":"F19","title":"Keyboard F19","description":"Not required to be supported by any OS","printable":false,"separator":true,"breaking":false,"modifier":false},"367":{"id":"F20","title":"Keyboard F20","description":"Not required to be supported by any OS","printable":false,"separator":true,"breaking":false,"modifier":false},"368":{"id":"F21","title":"Keyboard F21","description":"Not required to be supported by any OS","printable":false,"separator":true,"breaking":false,"modifier":false},"369":{"id":"F22","title":"Keyboard F22","description":"Not required to be supported by any OS","printable":false,"separator":true,"breaking":false,"modifier":false},"370":{"id":"F23","title":"Keyboard F23","description":"Not required to be supported by any OS","printable":false,"separator":true,"breaking":false,"modifier":false},"371":{"id":"F24","title":"Keyboard F24","description":"Not required to be supported by any OS","printable":false,"separator":true,"breaking":false,"modifier":false}}},{"name":"Mouse","description":"Mouse Actions","icon":"mouse","actions":{"560":{"id":"MS_CLICK_BWD","printable":false,"breaking":true,"name":"MOUSE_BACKWARD_CLICK","title":"Mouse Backward Button Click","icon":"drag_click","separator":true,"modifier":false},"561":{"id":"MS_CLICK_FWD","printable":false,"breaking":true,"name":"MOUSE_FORWARD_CLICK","title":"Mouse Forward Button Click","icon":"ads_click","separator":true,"modifier":false},"562":{"id":"MS_CLICK_LF","printable":false,"breaking":true,"name":"MOUSE_LEFT_CLICK","title":"Mouse Left Click","icon":"left_click","separator":true,"modifier":false},"563":{"id":"MS_CLICK_RT","printable":false,"breaking":true,"name":"MOUSE_RIGHT_CLICK","title":"Mouse Right Click","icon":"right_click","separator":true,"modifier":false},"564":{"id":"MS_CLICK_MD","printable":false,"breaking":true,"name":"MOUSE_MIDDLE_CLICK","title":"Mouse Middle Click","icon":"touchpad_mouse","separator":true,"modifier":false},"565":{"id":"MS_MOVE_RT","printable":false,"breaking":true,"name":"MOUSE_MOVE_RIGHT","title":"Mouse Move Right","icon":"arrow_circle_right","separator":true,"modifier":false},"566":{"id":"MS_MOVE_LF","printable":false,"breaking":true,"name":"MOUSE_MOVE_LEFT","title":"Mouse Move Left","icon":"arrow_circle_left","separator":true,"modifier":false},"567":{"id":"MS_MOVE_DN","printable":false,"breaking":true,"name":"MOUSE_MOVE_DOWN","title":"Mouse Move Down","icon":"arrow_circle_down","separator":true,"modifier":false},"568":{"id":"MS_MOVE_UP","printable":false,"breaking":true,"name":"MOUSE_MOVE_UP","title":"Mouse Move Up","icon":"arrow_circle_up","separator":true,"modifier":false},"569":{"id":"MS_SCRL_RT","printable":false,"breaking":true,"name":"MOUSE_SCROLL_RIGHT","title":"Mouse Scroll Right","icon":"swipe_right","separator":true,"modifier":false},"570":{"id":"MS_SCRL_LF","printable":false,"breaking":true,"name":"MOUSE_SCROLL_LEFT","title":"Mouse Scroll Left","icon":"swipe_left","separator":true,"modifier":false},"571":{"id":"MS_SCRL_DN","printable":false,"name":"MOUSE_SCROLL_DOWN","title":"Mouse Scroll Down","icon":"swipe_down","separator":true,"breaking":false,"modifier":false},"572":{"id":"MS_SCRL_UP","printable":false,"name":"MOUSE_SCROLL_UP","title":"Mouse Scroll Up","icon":"swipe_up","separator":true,"breaking":false,"modifier":false},"589":{"id":"MS_SPIN_SCRL_H_1","icon":"gamepad_circle_up","title":"Spin Pan North","printable":false,"separator":true,"breaking":false,"modifier":false},"590":{"id":"MS_SPIN_SCRL_H_2","icon":"gamepad_circle_right","title":"Spin Pan East","printable":false,"separator":true,"breaking":false,"modifier":false},"591":{"id":"MS_SPIN_SCRL_H_3","icon":"gamepad_circle_down","title":"Spin Pan South","printable":false,"separator":true,"breaking":false,"modifier":false},"592":{"id":"MS_SPIN_SCRL_H_4","icon":"gamepad_circle_left","title":"Spin Pan West","printable":false,"separator":true,"breaking":false,"modifier":false},"593":{"id":"MS_SPIN_SCRL_V_1","icon":"gamepad_circle_up","title":"Spin Scroll North","printable":false,"separator":true,"breaking":false,"modifier":false},"594":{"id":"MS_SPIN_SCRL_V_2","icon":"gamepad_circle_right","title":"Spin Scroll East","printable":false,"separator":true,"breaking":false,"modifier":false},"595":{"id":"MS_SPIN_SCRL_V_3","icon":"gamepad_circle_down","title":"Spin Scroll South","printable":false,"separator":true,"breaking":false,"modifier":false},"596":{"id":"MS_SPIN_SCRL_V_4","icon":"gamepad_circle_left","title":"Spin Scroll West","printable":false,"separator":true,"breaking":false,"modifier":false}}},{"name":"Chording","description":"CharaChorder specific actions","actions":{"575":{"id":"QUICKFIX","title":"Quickfix","icon":"bolt","printable":false,"separator":false,"description":"Delete the last chord attempt\n","breaking":false,"modifier":false},"573":{"id":"CAPITALIZE","description":"Capitalizes the next chord, or the current chord when used as an\noutput of a modifier.\n","icon":"uppercase","title":"Capitalize","printable":false,"separator":false,"demos":["actions.capitalize"],"breaking":false,"modifier":false},"574":{"id":"JOIN","title":"Join","icon":"join_inner","printable":false,"separator":false,"breaking":false,"description":"Delete the concatenator of the previous chord\n","modifier":false},"256":{"id":"KSC_00","icon":"block","title":"Inhibit Concatenator","description":"Prevent concatenator after this chord\n","printable":false,"separator":true,"breaking":false,"modifier":false},"1001":{"id":"ARPEGGIATE","icon":"combine_columns","title":"Arpeggiate Chord","printable":true,"separator":false,"breaking":false,"modifier":false},"1002":{"id":"TAP_DANCE","icon":"animation","title":"Tap Dance Chord","printable":true,"separator":false,"breaking":false,"modifier":false},"545":{"id":"HYPERSPACE","icon":"trail_length_medium","title":"Hyperspace","description":"Insert the current concatenator set by Hyperspace Capture\n","printable":true,"separator":false,"breaking":false,"modifier":false},"547":{"id":"CAPTURE","title":"Hyperspace Capture","icon":"blur_short","description":"Use in a chord output to capture hyperspace outputs.\nYou have to put this action both at the start and at the end of what you are capturing.\n","printable":false,"separator":false,"demos":["hyperspace.general"],"breaking":false,"modifier":false},"558":{"id":"HOLD_COMPOUND","title":"Dynamic Library","icon":"layers","description":"Allows for the activation & creation of dynamic chord libraries.\nWhen included as part of a chord output,\nthat chord's input becomes the seed for a dynamic chord library,\nand that library is activated.\nAny new chords created while a dynamic library is active are established one level above its seed.\n","printable":false,"separator":true,"breaking":false,"modifier":false},"559":{"id":"RELEASE_COMPOUND","title":"Base Library","icon":"layers_clear","description":"Re-activates your base chord library,\nand deactivates any currently active dynamic chord library.\n","printable":false,"separator":true,"breaking":false,"modifier":false},"598":{"id":"DELAY_1000","icon":"clock_loader_90","title":"Delay 1000ms","description":"Wait for 1000 milliseconds","printable":true,"separator":false,"breaking":false,"modifier":false},"597":{"id":"DELAY_500","icon":"clock_loader_80","title":"Delay 500ms","description":"Wait for 500 milliseconds","printable":true,"separator":false,"breaking":false,"modifier":false},"577":{"id":"DELAY_100","icon":"clock_loader_60","title":"Delay 100ms","description":"Wait for 100 milliseconds","printable":true,"separator":false,"breaking":false,"modifier":false},"578":{"id":"DELAY_10","icon":"clock_loader_40","title":"Delay 10ms","description":"Wait for 10 milliseconds","printable":true,"separator":false,"breaking":false,"modifier":false},"579":{"id":"DELAY_1","icon":"clock_loader_10","title":"Delay 1ms","description":"Wait for one millisecond","printable":true,"separator":false,"breaking":false,"modifier":false},"523":{"id":"PRESS_NEXT","title":"Press and do not release the next key/action","icon":"download","printable":false,"separator":false,"breaking":false,"modifier":false},"524":{"id":"RELEASE_NEXT","title":"Release the next key/action in the sequence","icon":"upload","printable":false,"separator":false,"breaking":false,"modifier":false}}},{"name":"Pseudo Actions","description":"These actions don't do anything, and can be used for single-key chords\n","actions":{"600":{"id":"LH_THUMB_3_3D","display":"01","title":"Pseudo 01","printable":false,"separator":true,"breaking":false,"modifier":false},"601":{"id":"LH_THUMB_2_3D","title":"Pseudo 02","display":"02","printable":false,"separator":true,"breaking":false,"modifier":false},"602":{"id":"LH_THUMB_1_3D","title":"Pseudo 03","display":"03","printable":false,"separator":true,"breaking":false,"modifier":false},"603":{"id":"LH_INDEX_3D","title":"Pseudo 04","display":"04","printable":false,"separator":true,"breaking":false,"modifier":false},"604":{"id":"LH_MID_1_3D","title":"Pseudo 05","display":"05","printable":false,"separator":true,"breaking":false,"modifier":false},"605":{"id":"LH_RING_1_3D","title":"Pseudo 06","display":"06","printable":false,"separator":true,"breaking":false,"modifier":false},"606":{"id":"LH_PINKY_3D","title":"Pseudo 07","display":"07","printable":false,"separator":true,"breaking":false,"modifier":false},"607":{"id":"LH_MID_2_3D","title":"Pseudo 08","display":"08","printable":false,"separator":true,"breaking":false,"modifier":false},"608":{"id":"LH_RING_2_3D","title":"Pseudo 09","display":"09","printable":false,"separator":true,"breaking":false,"modifier":false},"609":{"id":"RH_THUMB_3_3D","title":"Pseudo 10","display":"10","printable":false,"separator":true,"breaking":false,"modifier":false},"610":{"id":"RH_THUMB_2_3D","title":"Pseudo 11","display":"11","printable":false,"separator":true,"breaking":false,"modifier":false},"611":{"id":"RH_THUMB_1_3D","title":"Pseudo 12","display":"12","printable":false,"separator":true,"breaking":false,"modifier":false},"612":{"id":"RH_INDEX_3D","title":"Pseudo 13","display":"13","printable":false,"separator":true,"breaking":false,"modifier":false},"613":{"id":"RH_MID_1_3D","title":"Pseudo 14","display":"14","printable":false,"separator":true,"breaking":false,"modifier":false},"614":{"id":"RH_RING_1_3D","title":"Pseudo 15","display":"15","printable":false,"separator":true,"breaking":false,"modifier":false},"615":{"id":"RH_PINKY_3D","title":"Pseudo 16","display":"16","printable":false,"separator":true,"breaking":false,"modifier":false},"616":{"id":"RH_MID_2_3D","title":"Pseudo 17","display":"17","printable":false,"separator":true,"breaking":false,"modifier":false},"617":{"id":"RH_RING_2_3D","title":"Pseudo 18","display":"18","printable":false,"separator":true,"breaking":false,"modifier":false}}},{"name":"Modes","actions":{"531":{"id":"VIM","title":"VIM Mode","description":"Enter universal VIM emulation mode.\nEquivalent to normal mode in VIM.\nSupports a subset of VIM motions in any text box.\n","breaking":true,"printable":false,"separator":true,"modifier":false},"532":{"id":"GTM","name":"GTM_TOGGLE","title":"GTM Toggle","icon":"terminal","description":"Text based menu which is accessible anywhere you can type.\nIt allows you to access various device settings and features\nwithout the need for software and is activated by chording both alt keys together.\n","breaking":true,"printable":false,"separator":true,"modifier":false},"534":{"id":"IMPULSE","name":"IMPULSE_TOGGLE","title":"Impulse Toggle","icon":"heap_snapshot_multiple","description":"An 'on-the-fly' custom chord which can be spontaneously created anywhere that you can type via the GTM\n","breaking":true,"printable":false,"separator":true,"modifier":false},"538":{"id":"SPUR","name":"SPUR_TOGGLE","title":"Spurring Toggle","icon":"piano","description":"'Chording only' mode which tells your device to output chords on a press rather than a press & release.\nIt also enables you to jump from one chord to another without releasing everything and can be activated\nin GTM or by chording both mirror keys. It can provide significant speed gains with chording,\nbut also takes away the flexibility of character entry.\nSpurring also helps new users learn how to chord by eliminating the need to focus on timing.\nSpurring is toggled by chording both of the 'mirror' keys together.\n","printable":false,"breaking":true,"separator":true,"modifier":false},"576":{"id":"ACTIVE_QUICKFIX","title":"Active Quickfix","icon":"thunderstorm","printable":false,"separator":false,"description":"Delete the last chord attempt and enter active mode,\nwhere each new attempt replaces the previous one until\na successful chord attempt is hit or escape was pressed.\n","breaking":false,"modifier":false}}},{"name":"International","description":"Macros for the US-Intl. layout.\nExact mappings may vary depending on the system and specific variation of the layout.\n","actions":{"700":{"id":"ALT_R_SPACE","icon":"space_bar","description":"SPACE + AltGr","printable":true,"separator":false,"breaking":false,"modifier":false},"701":{"id":"\u00a1","description":"1 + Shift + AltGr","printable":true,"separator":false,"breaking":false,"modifier":false},"702":{"id":"DEAD_DIAERESIS","description":"Quote + Shift + AltGr","printable":true,"separator":false,"breaking":false,"modifier":false},"703":{"id":"DEAD_MACRON","description":"3 + Shift + AltGr","printable":true,"separator":false,"breaking":false,"modifier":false},"704":{"id":"\u00a3","description":"1 + Shift + AltGr","printable":true,"separator":false,"breaking":false,"modifier":false},"705":{"id":"DEAD_CEDILLA","description":"5 + Shift + AltGr","printable":true,"separator":false,"breaking":false,"modifier":false},"706":{"id":"\u00bd","description":"7 + Shift + AltGr","printable":true,"separator":false,"breaking":false,"modifier":false},"707":{"id":"DEAD_ACUTE","description":"Quote + AltGr","printable":true,"separator":false,"breaking":false,"modifier":false},"708":{"id":"DEAD_BREVE","description":"9 + Shift + AltGr","printable":true,"separator":false,"breaking":false,"modifier":false},"709":{"id":"DEAD_OVERRING","description":"0 + Shift + AltGr","printable":true,"separator":false,"breaking":false,"modifier":false},"710":{"id":"\u00be","description":"8 + Shift + AltGr","printable":true,"separator":false,"breaking":false,"modifier":false},"711":{"id":"\u00f7","description":"Equal + Shift + AltGr","printable":true,"separator":false,"breaking":false,"modifier":false},"712":{"id":"\u00e7","description":"Comma + AltGr","printable":true,"separator":false,"breaking":false,"modifier":false},"713":{"id":"\u00a5","description":"Minus + AltGr","printable":true,"separator":false,"breaking":false,"modifier":false},"714":{"id":"DEAD_OVERDOT","description":"Period + AltGr","printable":true,"separator":false,"breaking":false,"modifier":false},"715":{"id":"\u00bf","description":"Slash + AltGr","printable":true,"separator":false,"breaking":false,"modifier":false},"716":{"id":"\u2019","description":"0 + AltGr","printable":true,"separator":false,"breaking":false,"modifier":false},"717":{"id":"\u00b9","description":"1 + AltGr","printable":true,"separator":false,"breaking":false,"modifier":false},"718":{"id":"\u00b2","description":"2 + AltGr","printable":true,"separator":false,"breaking":false,"modifier":false},"719":{"id":"\u00b3","description":"3 + AltGr","printable":true,"separator":false,"breaking":false,"modifier":false},"720":{"id":"\u00a4","description":"4 + AltGr","printable":true,"separator":false,"breaking":false,"modifier":false},"721":{"id":"\u20ac","description":"5 + AltGr","printable":true,"separator":false,"breaking":false,"modifier":false},"722":{"id":"DEAD_CARET","description":"6 + AltGr","printable":true,"separator":false,"breaking":false,"modifier":false},"723":{"id":"DEAD_DOUBLE_QUOTE","description":"7 + AltGr","printable":true,"separator":false,"breaking":false,"modifier":false},"724":{"id":"DEAD_HOOK_RIGHT","description":"8 + AltGr","printable":true,"separator":false,"breaking":false,"modifier":false},"725":{"id":"\u2018","description":"9 + AltGr","printable":true,"separator":false,"breaking":false,"modifier":false},"726":{"id":"\u00b0","description":"Semicolon + Shift + AltGr","printable":true,"separator":false,"breaking":false,"modifier":false},"727":{"id":"\u00b6","description":"Semicolon + AltGr","printable":true,"separator":false,"breaking":false,"modifier":false},"728":{"id":"\u00c7","description":"Comma + Shift + AltGr","printable":true,"separator":false,"breaking":false,"modifier":false},"729":{"id":"\u00d7","description":"Equals + AltGr","printable":true,"separator":false,"breaking":false,"modifier":false},"730":{"id":"DEAD_CARON","description":"Period + Shift + AltGr","printable":true,"separator":false,"breaking":false,"modifier":false},"731":{"id":"DEAD_HOOK_ABOVE","description":"Slash + Shift + AltGr","printable":true,"separator":false,"breaking":false,"modifier":false},"732":{"id":"ALT_R_SHIFT_2","description":"2 + Shift + AltGr","printable":true,"separator":false,"breaking":false,"modifier":false},"733":{"id":"\u00c1","description":"a + Shift + AltGr","printable":true,"separator":false,"breaking":false,"modifier":false},"734":{"id":"DEAD_SLASH","description":"b + Shift + AltGr","printable":true,"separator":false,"breaking":false,"modifier":false},"735":{"id":"\u00a2","description":"c + Shift + AltGr","printable":true,"separator":false,"breaking":false,"modifier":false},"736":{"id":"\u00d0","description":"d + Shift + AltGr","printable":true,"separator":false,"breaking":false,"modifier":false},"737":{"id":"\u00c9","description":"e + Shift + AltGr","printable":true,"separator":false,"breaking":false,"modifier":false},"738":{"id":"ALT_R_SHIFT_F","description":"f + Shift + AltGr","printable":true,"separator":false,"breaking":false,"modifier":false},"739":{"id":"ALT_R_SHIFT_G","description":"g + Shift + AltGr","printable":true,"separator":false,"breaking":false,"modifier":false},"740":{"id":"ALT_R_SHIFT_H","description":"h + Shift + AltGr","printable":true,"separator":false,"breaking":false,"modifier":false},"741":{"id":"\u00cd","description":"i + Shift + AltGr","printable":true,"separator":false,"breaking":false,"modifier":false},"742":{"id":"\u00cf","description":"j + Shift + AltGr","printable":true,"separator":false,"breaking":false,"modifier":false},"743":{"id":"\u0152","description":"k + Shift + AltGr","printable":true,"separator":false,"breaking":false,"modifier":false},"744":{"id":"\u00d8","description":"l + Shift + AltGr","printable":true,"separator":false,"breaking":false,"modifier":false},"745":{"id":"\u00b1","description":"m + Shift + AltGr","printable":true,"separator":false,"breaking":false,"modifier":false},"746":{"id":"\u00d1","description":"n + Shift + AltGr","printable":true,"separator":false,"breaking":false,"modifier":false},"747":{"id":"\u00d3","description":"o + Shift + AltGr","printable":true,"separator":false,"breaking":false,"modifier":false},"748":{"id":"\u00d6","description":"p + Shift + AltGr","printable":true,"separator":false,"breaking":false,"modifier":false},"749":{"id":"\u00c4","description":"q + Shift + AltGr","printable":true,"separator":false,"breaking":false,"modifier":false},"750":{"id":"\u00cb","description":"r + Shift + AltGr","printable":true,"separator":false,"breaking":false,"modifier":false},"751":{"id":"\u00a7","description":"s + Shift + AltGr","printable":true,"separator":false,"breaking":false,"modifier":false},"752":{"id":"\u00de","description":"t + Shift + AltGr","printable":true,"separator":false,"breaking":false,"modifier":false},"753":{"id":"\u00da","description":"u + Shift + AltGr","printable":true,"separator":false,"breaking":false,"modifier":false},"754":{"id":"\u2122","description":"v + Shift + AltGr","printable":true,"separator":false,"breaking":false,"modifier":false},"755":{"id":"\u00c5","description":"w + Shift + AltGr","printable":true,"separator":false,"breaking":false,"modifier":false},"756":{"id":"ALT_R_SHIFT_X","description":"x + Shift + AltGr","printable":true,"separator":false,"breaking":false,"modifier":false},"757":{"id":"\u00dc","description":"y + Shift + AltGr","printable":true,"separator":false,"breaking":false,"modifier":false},"758":{"id":"\u00c6","description":"z + Shift + AltGr","printable":true,"separator":false,"breaking":false,"modifier":false},"759":{"id":"\u00ab","description":"Left Bracket + AltGr","printable":true,"separator":false,"breaking":false,"modifier":false},"760":{"id":"\u00ac","description":"Backslash + AltGr","printable":true,"separator":false,"breaking":false,"modifier":false},"761":{"id":"\u00bb","description":"Right Bracket + AltGr","printable":true,"separator":false,"breaking":false,"modifier":false},"762":{"id":"\u00bc","description":"6 + Shift + AltGr","printable":true,"separator":false,"breaking":false,"modifier":false},"763":{"id":"DEAD_UNDERDOT","description":"Minus + Shift + AltGr","printable":true,"separator":false,"breaking":false,"modifier":false},"764":{"id":"DEAD_GRAVE","description":"Grave + AltGr","printable":true,"separator":false,"breaking":false,"modifier":false},"765":{"id":"\u00e1","description":"a + AltGr","printable":true,"separator":false,"breaking":false,"modifier":false},"766":{"id":"\u00b7","description":"b + AltGr","printable":true,"separator":false,"breaking":false,"modifier":false},"767":{"id":"\u00a9","description":"c + AltGr","printable":true,"separator":false,"breaking":false,"modifier":false},"768":{"id":"\u00f0","description":"d + AltGr","printable":true,"separator":false,"breaking":false,"modifier":false},"769":{"id":"\u00e9","description":"e + AltGr","printable":true,"separator":false,"breaking":false,"modifier":false},"770":{"id":"ALT_R_f","description":"f + AltGr","printable":true,"separator":false,"breaking":false,"modifier":false},"771":{"id":"ALT_R_g","description":"g + AltGr","printable":true,"separator":false,"breaking":false,"modifier":false},"772":{"id":"ALT_R_h","description":"h + AltGr","printable":true,"separator":false,"breaking":false,"modifier":false},"773":{"id":"\u00ed","description":"i + AltGr","printable":true,"separator":false,"breaking":false,"modifier":false},"774":{"id":"\u00ef","description":"j + AltGr","printable":true,"separator":false,"breaking":false,"modifier":false},"775":{"id":"\u0153","description":"k + AltGr","printable":true,"separator":false,"breaking":false,"modifier":false},"776":{"id":"\u00f8","description":"l + AltGr","printable":true,"separator":false,"breaking":false,"modifier":false},"777":{"id":"\u00b5","description":"m + AltGr","printable":true,"separator":false,"breaking":false,"modifier":false},"778":{"id":"\u00f1","description":"n + AltGr","printable":true,"separator":false,"breaking":false,"modifier":false},"779":{"id":"\u00f3","description":"o + AltGr","printable":true,"separator":false,"breaking":false,"modifier":false},"780":{"id":"\u00f6","description":"p + AltGr","printable":true,"separator":false,"breaking":false,"modifier":false},"781":{"id":"\u00e4","description":"q + AltGr","printable":true,"separator":false,"breaking":false,"modifier":false},"782":{"id":"\u00eb","description":"r + AltGr","printable":true,"separator":false,"breaking":false,"modifier":false},"783":{"id":"\u00df","description":"s + AltGr","printable":true,"separator":false,"breaking":false,"modifier":false},"784":{"id":"\u00fe","description":"t + AltGr","printable":true,"separator":false,"breaking":false,"modifier":false},"785":{"id":"\u00fa","description":"u + AltGr","printable":true,"separator":false,"breaking":false,"modifier":false},"786":{"id":"\u00ae","description":"v + AltGr","printable":true,"separator":false,"breaking":false,"modifier":false},"787":{"id":"\u00e5","description":"w + AltGr","printable":true,"separator":false,"breaking":false,"modifier":false},"788":{"id":"ALT_R_X","description":"x + AltGr","printable":true,"separator":false,"breaking":false,"modifier":false},"789":{"id":"\u00fc","description":"y + AltGr","printable":true,"separator":false,"breaking":false,"modifier":false},"790":{"id":"\u00e6","description":"z + AltGr","printable":true,"separator":false,"breaking":false,"modifier":false},"791":{"id":"\u201c","description":"Left Bracket + Shift + AltGr","printable":true,"separator":false,"breaking":false,"modifier":false},"792":{"id":"\u00a6","description":"Backslash + Shift + AltGr","printable":true,"separator":false,"breaking":false,"modifier":false},"793":{"id":"\u201d","description":"Right Bracket + Shift + AltGr","printable":true,"separator":false,"breaking":false,"modifier":false},"794":{"id":"DEAD_TILDE","description":"Grave + Shift + AltGr","printable":true,"separator":false,"breaking":false,"modifier":false},"795":{"id":"ALT_R_DEL","description":"DEL + AltGr","printable":true,"separator":false,"breaking":false,"modifier":false},"798":{"id":"ALT_R_ISO_BACKSLASH","description":"ISO_BACKSLASH + AltGr","printable":true,"separator":false,"breaking":false,"modifier":false},"799":{"id":"SHIFT_ALT_R_ISO_BACKSLASH","description":"ISO_BACKSLASH + Shift + AltGr","printable":true,"separator":false,"breaking":false,"modifier":false}}},{"name":"Windows Alt Codes","description":"Special characters that can be inserted on Windows by holding ALT and typing a code on the Numpad.","actions":{"128":{"id":"\u20ac (Windows Alt Code)","name":"EURO","title":"Uppercase cedilla","printable":true,"separator":false,"breaking":false,"modifier":false},"129":{"id":"HOP","title":"HOP (High Octet Preset)","printable":true,"separator":false,"breaking":false,"modifier":false},"130":{"id":"\u201a","title":"Single Low-9 Quotation Mark","printable":true,"separator":false,"breaking":false,"modifier":false},"131":{"id":"\u0192","title":"Latin Small Letter f with Hook; Florin","printable":true,"separator":false,"breaking":false,"modifier":false},"132":{"id":"\u201e","title":"Double Low-9 Quotation Mark","printable":true,"separator":false,"breaking":false,"modifier":false},"133":{"id":"\u2026","title":"Horizontal Ellipsis","printable":true,"separator":false,"breaking":false,"modifier":false},"134":{"id":"\u2020","title":"Dagger","printable":true,"separator":false,"breaking":false,"modifier":false},"135":{"id":"\u2021","title":"Double Dagger","printable":true,"separator":false,"breaking":false,"modifier":false},"136":{"id":"\u02c6","title":"Circumflex","printable":true,"separator":false,"breaking":false,"modifier":false},"137":{"id":"\u2030","title":"Per Mile","printable":true,"separator":false,"breaking":false,"modifier":false},"138":{"id":"\u0160","title":"Captial S Caron","printable":true,"separator":false,"breaking":false,"modifier":false},"139":{"id":"\u2039","title":"Left Guillemet","printable":true,"separator":false,"breaking":false,"modifier":false},"140":{"id":"\u0152 (Windows Alt Code)","title":"Captial Ligature OE","printable":true,"separator":false,"breaking":false,"modifier":false},"141":{"name":"REVERSE_INDEX","title":"RI (Reverse Index)","printable":true,"separator":false,"breaking":false,"modifier":false},"142":{"id":"\u017d","title":"Captial Z Caron","printable":true,"separator":false,"breaking":false,"modifier":false},"143":{"name":"SS3","title":"SS3 (Single-Shift G3)","printable":true,"separator":false,"breaking":false,"modifier":false},"144":{"name":"DCS","title":"DCS (Device Control String)","printable":true,"separator":false,"breaking":false,"modifier":false},"145":{"id":"\u2018 (Windows Alt Code)","title":"Single Quote Left","printable":true,"separator":false,"breaking":false,"modifier":false},"146":{"id":"\u2019 (Windows Alt Code)","title":"Single Quote Right","printable":true,"separator":false,"breaking":false,"modifier":false},"147":{"id":"\u201c (Windows Alt Code)","title":"Double Quote Left","printable":true,"separator":false,"breaking":false,"modifier":false},"148":{"id":"\u201d (Windows Alt Code)","title":"Double Quote Right","printable":true,"separator":false,"breaking":false,"modifier":false},"149":{"id":"\u2022","title":"Bullet","printable":true,"separator":false,"breaking":false,"modifier":false},"150":{"id":"\u2013","title":"En Dash","printable":true,"separator":false,"breaking":false,"modifier":false},"151":{"id":"\u2014","title":"Em Dash","printable":true,"separator":false,"breaking":false,"modifier":false},"152":{"id":"\u02dc","title":"Small Tilde","printable":true,"separator":false,"breaking":false,"modifier":false},"153":{"id":"\u2122 (Windows Alt Code)","title":"Trademark","printable":true,"separator":false,"breaking":false,"modifier":false},"154":{"id":"\u0161","title":"Small s Carson","printable":true,"separator":false,"breaking":false,"modifier":false},"155":{"id":"\u203a","title":"Right Guillement","printable":true,"separator":false,"breaking":false,"modifier":false},"156":{"id":"\u0153 (Windows Alt Code)","title":"Small Ligature oe","printable":true,"separator":false,"breaking":false,"modifier":false},"157":{"title":"Operating System Command","printable":true,"separator":false,"breaking":false,"modifier":false},"158":{"id":"\u017e","title":"Small Z Caron","printable":true,"separator":false,"breaking":false,"modifier":false},"159":{"id":"\u0178","title":"Capital Y Diaresis","printable":true,"separator":false,"breaking":false,"modifier":false},"160":{"id":"NO_BREAK_SPACE","title":"No Break Space","printable":true,"separator":false,"breaking":false,"modifier":false},"161":{"id":"\u00a1 (Windows Alt Code)","title":"Inverted Exclamation","printable":true,"separator":false,"breaking":false,"modifier":false},"162":{"id":"\u00a2 (Windows Alt Code)","title":"Cent","printable":true,"separator":false,"breaking":false,"modifier":false},"163":{"id":"\u00a3 (Windows Alt Code)","title":"Pound","printable":true,"separator":false,"breaking":false,"modifier":false},"164":{"id":"\u00a4 (Windows Alt Code)","title":"Currency","printable":true,"separator":false,"breaking":false,"modifier":false},"165":{"id":"\u00a5 (Windows Alt Code)","title":"Yen","printable":true,"separator":false,"breaking":false,"modifier":false},"166":{"id":"\u00a6 (Windows Alt Code)","title":"Broken Bar","printable":true,"separator":false,"breaking":false,"modifier":false},"167":{"id":"\u00a7 (Windows Alt Code)","title":"Section","printable":true,"separator":false,"breaking":false,"modifier":false},"168":{"id":"\u00a8","title":"Diaresis","printable":true,"separator":false,"breaking":false,"modifier":false},"169":{"id":"\u00a9 (Windows Alt Code)","title":"Copyright","printable":true,"separator":false,"breaking":false,"modifier":false},"170":{"id":"\u00aa","title":"Feminine Ordinal","printable":true,"separator":false,"breaking":false,"modifier":false},"171":{"id":"\u00ab (Windows Alt Code)","title":"Double Left Guillement","printable":true,"separator":false,"breaking":false,"modifier":false},"172":{"id":"\u00ac (Windows Alt Code)","title":"Not","printable":true,"separator":false,"breaking":false,"modifier":false},"173":{"id":"\u00ad","title":"Soft Hyphen","printable":true,"separator":false,"breaking":false,"modifier":false},"174":{"id":"\u00ae (Windows Alt Code)","title":"Registered","printable":true,"separator":false,"breaking":false,"modifier":false},"175":{"id":"\u00af","title":"Macron","printable":true,"separator":false,"breaking":false,"modifier":false},"176":{"id":"\u00b0 (Windows Alt Code)","title":"Degree","printable":true,"separator":false,"breaking":false,"modifier":false},"177":{"id":"\u00b1 (Windows Alt Code)","title":"Plus Minus","printable":true,"separator":false,"breaking":false,"modifier":false},"178":{"id":"\u00b2 (Windows Alt Code)","title":"Superscript Two","printable":true,"separator":false,"breaking":false,"modifier":false},"179":{"id":"\u00b3 (Windows Alt Code)","title":"Superscript Three","printable":true,"separator":false,"breaking":false,"modifier":false},"180":{"id":"\u00b4","title":"Acute","printable":true,"separator":false,"breaking":false,"modifier":false},"181":{"id":"\u00b5 (Windows Alt Code)","title":"Micro","printable":true,"separator":false,"breaking":false,"modifier":false},"182":{"id":"\u00b6 (Windows Alt Code)","title":"Pilcrow","printable":true,"separator":false,"breaking":false,"modifier":false},"183":{"id":"\u00b7 (Windows Alt Code)","title":"Middle Dot","printable":true,"separator":false,"breaking":false,"modifier":false},"184":{"id":"\u00b8","title":"Cedilla","printable":true,"separator":false,"breaking":false,"modifier":false},"185":{"id":"\u00b9 (Windows Alt Code)","title":"Superscript One","printable":true,"separator":false,"breaking":false,"modifier":false},"186":{"id":"\u00ba","title":"Masculine Ordinal","printable":true,"separator":false,"breaking":false,"modifier":false},"187":{"id":"\u00bb (Windows Alt Code)","title":"Double Right Guillement","printable":true,"separator":false,"breaking":false,"modifier":false},"188":{"id":"\u00bc (Windows Alt Code)","title":"One Quarter Fraction","printable":true,"separator":false,"breaking":false,"modifier":false},"189":{"id":"\u00bd (Windows Alt Code)","title":"One Half Fraction","printable":true,"separator":false,"breaking":false,"modifier":false},"190":{"id":"\u00be (Windows Alt Code)","title":"Three Quarters Fraction","printable":true,"separator":false,"breaking":false,"modifier":false},"191":{"id":"\u00bf (Windows Alt Code)","title":"Inverted Question","printable":true,"separator":false,"breaking":false,"modifier":false},"192":{"id":"\u00c0","title":"Captial A Grave","printable":true,"separator":false,"breaking":false,"modifier":false},"193":{"id":"\u00c1 (Windows Alt Code)","printable":true,"separator":false,"breaking":false,"modifier":false},"194":{"id":"\u00c2","printable":true,"separator":false,"breaking":false,"modifier":false},"195":{"id":"\u00c3","printable":true,"separator":false,"breaking":false,"modifier":false},"196":{"id":"\u00c4 (Windows Alt Code)","printable":true,"separator":false,"breaking":false,"modifier":false},"197":{"id":"\u00c5 (Windows Alt Code)","printable":true,"separator":false,"breaking":false,"modifier":false},"198":{"id":"\u00c6 (Windows Alt Code)","printable":true,"separator":false,"breaking":false,"modifier":false},"199":{"id":"\u00c7 (Windows Alt Code)","printable":true,"separator":false,"breaking":false,"modifier":false},"200":{"id":"\u00c8","printable":true,"separator":false,"breaking":false,"modifier":false},"201":{"id":"\u00c9 (Windows Alt Code)","printable":true,"separator":false,"breaking":false,"modifier":false},"202":{"id":"\u00ca","printable":true,"separator":false,"breaking":false,"modifier":false},"203":{"id":"\u00cb (Windows Alt Code)","printable":true,"separator":false,"breaking":false,"modifier":false},"204":{"id":"\u00cc","printable":true,"separator":false,"breaking":false,"modifier":false},"205":{"id":"\u00cd (Windows Alt Code)","printable":true,"separator":false,"breaking":false,"modifier":false},"206":{"id":"\u00ce","printable":true,"separator":false,"breaking":false,"modifier":false},"207":{"id":"\u00cf (Windows Alt Code)","printable":true,"separator":false,"breaking":false,"modifier":false},"208":{"id":"\u00d0 (Windows Alt Code)","printable":true,"separator":false,"breaking":false,"modifier":false},"209":{"id":"\u00d1 (Windows Alt Code)","printable":true,"separator":false,"breaking":false,"modifier":false},"210":{"id":"\u00d2","printable":true,"separator":false,"breaking":false,"modifier":false},"211":{"id":"\u00d3 (Windows Alt Code)","printable":true,"separator":false,"breaking":false,"modifier":false},"212":{"id":"\u00d4","printable":true,"separator":false,"breaking":false,"modifier":false},"213":{"id":"\u00d5","printable":true,"separator":false,"breaking":false,"modifier":false},"214":{"id":"\u00d6 (Windows Alt Code)","printable":true,"separator":false,"breaking":false,"modifier":false},"215":{"id":"\u00d7 (Windows Alt Code)","printable":true,"separator":false,"breaking":false,"modifier":false},"216":{"id":"\u00d8 (Windows Alt Code)","printable":true,"separator":false,"breaking":false,"modifier":false},"217":{"id":"\u00d9","printable":true,"separator":false,"breaking":false,"modifier":false},"218":{"id":"\u00da (Windows Alt Code)","printable":true,"separator":false,"breaking":false,"modifier":false},"219":{"id":"\u00db","printable":true,"separator":false,"breaking":false,"modifier":false},"220":{"id":"\u00dc (Windows Alt Code)","printable":true,"separator":false,"breaking":false,"modifier":false},"221":{"id":"\u00dd","printable":true,"separator":false,"breaking":false,"modifier":false},"222":{"id":"\u00de (Windows Alt Code)","printable":true,"separator":false,"breaking":false,"modifier":false},"223":{"id":"\u00df (Windows Alt Code)","printable":true,"separator":false,"breaking":false,"modifier":false},"224":{"id":"\u00e0","printable":true,"separator":false,"breaking":false,"modifier":false},"225":{"id":"\u00e1 (Windows Alt Code)","printable":true,"separator":false,"breaking":false,"modifier":false},"226":{"id":"\u00e2","printable":true,"separator":false,"breaking":false,"modifier":false},"227":{"id":"\u00e3","printable":true,"separator":false,"breaking":false,"modifier":false},"228":{"id":"\u00e4 (Windows Alt Code)","printable":true,"separator":false,"breaking":false,"modifier":false},"229":{"id":"\u00e5 (Windows Alt Code)","printable":true,"separator":false,"breaking":false,"modifier":false},"230":{"id":"\u00e6 (Windows Alt Code)","printable":true,"separator":false,"breaking":false,"modifier":false},"231":{"id":"\u00e7 (Windows Alt Code)","printable":true,"separator":false,"breaking":false,"modifier":false},"232":{"id":"\u00e8","printable":true,"separator":false,"breaking":false,"modifier":false},"233":{"id":"\u00e9 (Windows Alt Code)","printable":true,"separator":false,"breaking":false,"modifier":false},"234":{"id":"\u00ea","printable":true,"separator":false,"breaking":false,"modifier":false},"235":{"id":"\u00eb (Windows Alt Code)","printable":true,"separator":false,"breaking":false,"modifier":false},"236":{"id":"\u00ec","printable":true,"separator":false,"breaking":false,"modifier":false},"237":{"id":"\u00ed (Windows Alt Code)","printable":true,"separator":false,"breaking":false,"modifier":false},"238":{"id":"\u00ee","printable":true,"separator":false,"breaking":false,"modifier":false},"239":{"id":"\u00ef (Windows Alt Code)","printable":true,"separator":false,"breaking":false,"modifier":false},"240":{"id":"\u00f0 (Windows Alt Code)","printable":true,"separator":false,"breaking":false,"modifier":false},"241":{"id":"\u00f1 (Windows Alt Code)","printable":true,"separator":false,"breaking":false,"modifier":false},"242":{"id":"\u00f2","printable":true,"separator":false,"breaking":false,"modifier":false},"243":{"id":"\u00f3 (Windows Alt Code)","printable":true,"separator":false,"breaking":false,"modifier":false},"244":{"id":"\u00f4","printable":true,"separator":false,"breaking":false,"modifier":false},"245":{"id":"\u00f5","printable":true,"separator":false,"breaking":false,"modifier":false},"246":{"id":"\u00f6 (Windows Alt Code)","printable":true,"separator":false,"breaking":false,"modifier":false},"247":{"id":"\u00f7 (Windows Alt Code)","printable":true,"separator":false,"breaking":false,"modifier":false},"248":{"id":"\u00f8 (Windows Alt Code)","printable":true,"separator":false,"breaking":false,"modifier":false},"249":{"id":"\u00f9","printable":true,"separator":false,"breaking":false,"modifier":false},"250":{"id":"\u00fa (Windows Alt Code)","printable":true,"separator":false,"breaking":false,"modifier":false},"251":{"id":"\u00fb","printable":true,"separator":false,"breaking":false,"modifier":false},"252":{"id":"\u00fc (Windows Alt Code)","printable":true,"separator":false,"breaking":false,"modifier":false},"253":{"id":"\u00fd","printable":true,"separator":false,"breaking":false,"modifier":false},"254":{"id":"\u00fe (Windows Alt Code)","printable":true,"separator":false,"breaking":false,"modifier":false},"255":{"id":"\u00ff","title":"Small y Diaeresis","printable":true,"separator":false,"breaking":false,"modifier":false}}},{"name":"Modifier Macros","actions":{"526":{"id":"HYPER","title":"Hyper key, holds left ctrl, shift, alt and gui","printable":false,"separator":true,"breaking":false,"modifier":false},"527":{"id":"MEH","title":"Meh key, holds left ctrl, shift and alt","printable":false,"separator":true,"breaking":false,"modifier":false},"525":{"id":"RIGHT_ALT_SHIFT","title":"AltGr and Shift in one action","printable":false,"separator":false,"modifier":true,"breaking":false},"620":{"id":"PRIMARY_SHIFT","title":"Holds shift with the primary layer","printable":false,"separator":false,"modifier":true,"breaking":false},"621":{"id":"PRIMARY_ALT_L","title":"Holds left alt with the primary layer","printable":false,"separator":false,"breaking":false,"modifier":false},"622":{"id":"PRIMARY_ALT_R","title":"Holds right alt (AltGr) with the primary layer","printable":false,"separator":false,"modifier":true,"breaking":false},"623":{"id":"PRIMARY_SHIFT_ALT_R","title":"Holds shift and right alt (AltGr) with the primary layer","printable":false,"separator":false,"modifier":true,"breaking":false},"624":{"id":"PRIMARY_CTRL","title":"Holds ctrl with the primary layer","printable":false,"separator":false,"breaking":false,"modifier":false},"625":{"id":"PRIMARY_GUI","title":"Holds gui with the primary layer","printable":false,"separator":false,"breaking":false,"modifier":false},"626":{"id":"PRIMARY_MEH","title":"Holds meh with the primary layer","printable":false,"separator":false,"breaking":false,"modifier":false},"627":{"id":"PRIMARY_HYPER","title":"Holds hyper with the primary layer","printable":false,"separator":false,"breaking":false,"modifier":false},"630":{"id":"SECONDARY_SHIFT","title":"Holds shift with the secondary layer","printable":false,"separator":false,"modifier":true,"breaking":false},"631":{"id":"SECONDARY_ALT_L","title":"Holds left alt with the secondary layer","printable":false,"separator":false,"breaking":false,"modifier":false},"632":{"id":"SECONDARY_ALT_R","title":"Holds right alt (AltGr) with the secondary layer","printable":false,"separator":false,"modifier":true,"breaking":false},"633":{"id":"SECONDARY_SHIFT_ALT_R","title":"Holds shift and right alt (AltGr) with the secondary layer","printable":false,"separator":false,"modifier":true,"breaking":false},"634":{"id":"SECONDARY_CTRL","title":"Holds ctrl with the secondary layer","printable":false,"separator":false,"breaking":false,"modifier":false},"635":{"id":"SECONDARY_GUI","title":"Holds gui with the secondary layer","printable":false,"separator":false,"breaking":false,"modifier":false},"636":{"id":"SECONDARY_MEH","title":"Holds meh with the secondary layer","printable":false,"separator":false,"breaking":false,"modifier":false},"637":{"id":"SECONDARY_HYPER","title":"Holds hyper with the secondary layer","printable":false,"separator":false,"breaking":false,"modifier":false},"640":{"id":"TERTIARY_SHIFT","title":"Holds shift with the tertiary layer","printable":false,"separator":false,"modifier":true,"breaking":false},"641":{"id":"TERTIARY_ALT_L","title":"Holds left alt with the tertiary layer","printable":false,"separator":false,"breaking":false,"modifier":false},"642":{"id":"TERTIARY_ALT_R","title":"Holds right alt (AltGr) with the tertiary layer","printable":false,"separator":false,"modifier":true,"breaking":false},"643":{"id":"TERTIARY_SHIFT_ALT_R","title":"Holds shift and right alt (AltGr) with the tertiary layer","printable":false,"separator":false,"modifier":true,"breaking":false},"644":{"id":"TERTIARY_CTRL","title":"Holds ctrl with the tertiary layer","printable":false,"separator":false,"breaking":false,"modifier":false},"645":{"id":"TERTIARY_GUI","title":"Holds gui with the tertiary layer","printable":false,"separator":false,"breaking":false,"modifier":false},"646":{"id":"TERTIARY_MEH","title":"Holds meh with the tertiary layer","printable":false,"separator":false,"breaking":false,"modifier":false},"647":{"id":"TERTIARY_HYPER","title":"Holds hyper with the tertiary layer","printable":false,"separator":false,"breaking":false,"modifier":false},"660":{"id":"QUATERNARY_SHIFT","title":"Holds shift with the tertiary layer","printable":false,"separator":false,"modifier":true,"breaking":false},"661":{"id":"QUATERNARY_ALT_L","title":"Holds left alt with the tertiary layer","printable":false,"separator":false,"breaking":false,"modifier":false},"662":{"id":"QUATERNARY_ALT_R","title":"Holds right alt (AltGr) with the tertiary layer","printable":false,"separator":false,"modifier":true,"breaking":false},"663":{"id":"QUATERNARY_SHIFT_ALT_R","title":"Holds shift and right alt (AltGr) with the tertiary layer","printable":false,"separator":false,"modifier":true,"breaking":false},"664":{"id":"QUATERNARY_CTRL","title":"Holds ctrl with the tertiary layer","printable":false,"separator":false,"breaking":false,"modifier":false},"665":{"id":"QUATERNARY_GUI","title":"Holds gui with the tertiary layer","printable":false,"separator":false,"breaking":false,"modifier":false},"666":{"id":"QUATERNARY_MEH","title":"Holds meh with the tertiary layer","printable":false,"separator":false,"breaking":false,"modifier":false},"667":{"id":"QUATERNARY_HYPER","title":"Holds hyper with the tertiary layer","printable":false,"separator":false,"breaking":false,"modifier":false}}},{"name":"ASCII","actions":{"32":{"id":"SPACE","icon":"space_bar","keyCode":"Space","separator":true,"alias":[300],"printable":true,"breaking":false,"modifier":false},"544":{"variantOf":36,"id":"SPACERIGHT","name":"SPACE_R","display":" ","title":"Right Spacebar (eg CC Lite)","icon":"space_bar","variant":"right","separator":true,"printable":true,"breaking":false,"modifier":false},"39":{"id":"'","name":"SINGLE_QUOTE","keyCode":"Quote","title":"Single Quote","alias":[308],"printable":true,"separator":false,"breaking":false,"modifier":false},"44":{"id":",","keyCode":"Comma","title":"Comma","alias":[310],"printable":true,"separator":false,"breaking":false,"modifier":false},"45":{"id":"-","keyCode":"Minus","title":"Minus","separator":true,"alias":[301],"printable":true,"breaking":false,"modifier":false},"46":{"id":".","keyCode":"Period","title":"Period","alias":[311],"printable":true,"separator":false,"breaking":false,"modifier":false},"47":{"id":"/","keyCode":"Slash","title":"Forward Slash","separator":true,"alias":[312],"printable":true,"breaking":false,"modifier":false},"48":{"id":"0","keyCode":"Digit0","title":"Zero","alias":[295],"printable":true,"separator":false,"breaking":false,"modifier":false},"49":{"id":"1","keyCode":"Digit1","title":"One","alias":[286],"printable":true,"separator":false,"breaking":false,"modifier":false},"50":{"id":"2","keyCode":"Digit2","title":"Two","alias":[287],"printable":true,"separator":false,"breaking":false,"modifier":false},"51":{"id":"3","keyCode":"Digit3","title":"Three","alias":[288],"printable":true,"separator":false,"breaking":false,"modifier":false},"52":{"id":"4","keyCode":"Digit4","title":"Four","alias":[289],"printable":true,"separator":false,"breaking":false,"modifier":false},"53":{"id":"5","keyCode":"Digit5","title":"Five","alias":[290],"printable":true,"separator":false,"breaking":false,"modifier":false},"54":{"id":"6","keyCode":"Digit6","title":"Six","alias":[291],"printable":true,"separator":false,"breaking":false,"modifier":false},"55":{"id":"7","keyCode":"Digit7","title":"Seven","alias":[292],"printable":true,"separator":false,"breaking":false,"modifier":false},"56":{"id":"8","keyCode":"Digit8","title":"Eight","alias":[293],"printable":true,"separator":false,"breaking":false,"modifier":false},"57":{"id":"9","keyCode":"Digit9","title":"Nine","alias":[294],"printable":true,"separator":false,"breaking":false,"modifier":false},"59":{"id":";","keyCode":"Semicolon","title":"Semicolon","alias":[307],"printable":true,"separator":false,"breaking":false,"modifier":false},"61":{"id":"=","keyCode":"Equal","title":"Equals","separator":true,"alias":[302],"printable":true,"breaking":false,"modifier":false},"91":{"id":"[","keyCode":"BracketLeft","title":"Left Bracket","separator":true,"alias":[303],"printable":true,"breaking":false,"modifier":false},"92":{"id":"\\","keyCode":"Backslash","title":"Backslash","separator":true,"alias":[305],"printable":true,"breaking":false,"modifier":false},"796":{"id":"\\ (ISO)","name":"ISO_BACKSLASH","title":"Keyboard Non-US \\ and | (US English)","separator":true,"keyCode":"IntlBackslash","description":"On ISO keyboards (L-shaped ENTER key) this extra key is found to the right of the left shift key.","alias":[356],"printable":true,"breaking":false,"modifier":false},"93":{"id":"]","keyCode":"BracketRight","title":"Right Bracket","separator":true,"alias":[304],"printable":true,"breaking":false,"modifier":false},"96":{"id":"`","name":"GRAVE","keyCode":"Backquote","title":"Backtick","separator":true,"alias":[309],"printable":true,"breaking":false,"modifier":false},"97":{"id":"a","keyCode":"KeyA","title":"Lowercase a","alias":[260],"printable":true,"separator":false,"breaking":false,"modifier":false},"98":{"id":"b","keyCode":"KeyB","title":"Lowercase b","alias":[261],"printable":true,"separator":false,"breaking":false,"modifier":false},"99":{"id":"c","keyCode":"KeyC","title":"Lowercase c","alias":[262],"printable":true,"separator":false,"breaking":false,"modifier":false},"100":{"id":"d","keyCode":"KeyD","title":"Lowercase d","alias":[263],"printable":true,"separator":false,"breaking":false,"modifier":false},"101":{"id":"e","keyCode":"KeyE","title":"Lowercase e","alias":[264],"printable":true,"separator":false,"breaking":false,"modifier":false},"102":{"id":"f","keyCode":"KeyF","title":"Lowercase f","alias":[265],"printable":true,"separator":false,"breaking":false,"modifier":false},"103":{"id":"g","keyCode":"KeyG","title":"Lowercase g","alias":[266],"printable":true,"separator":false,"breaking":false,"modifier":false},"104":{"id":"h","keyCode":"KeyH","title":"Lowercase h","alias":[267],"printable":true,"separator":false,"breaking":false,"modifier":false},"105":{"id":"i","keyCode":"KeyI","title":"Lowercase i","alias":[268],"printable":true,"separator":false,"breaking":false,"modifier":false},"106":{"id":"j","keyCode":"KeyJ","title":"Lowercase j","alias":[269],"printable":true,"separator":false,"breaking":false,"modifier":false},"107":{"id":"k","keyCode":"KeyK","title":"Lowercase k","alias":[270],"printable":true,"separator":false,"breaking":false,"modifier":false},"108":{"id":"l","keyCode":"KeyL","title":"Lowercase l","alias":[271],"printable":true,"separator":false,"breaking":false,"modifier":false},"109":{"id":"m","keyCode":"KeyM","title":"Lowercase m","alias":[272],"printable":true,"separator":false,"breaking":false,"modifier":false},"110":{"id":"n","keyCode":"KeyN","title":"Lowercase n","alias":[273],"printable":true,"separator":false,"breaking":false,"modifier":false},"111":{"id":"o","keyCode":"KeyO","title":"Lowercase o","alias":[274],"printable":true,"separator":false,"breaking":false,"modifier":false},"112":{"id":"p","keyCode":"KeyP","title":"Lowercase p","alias":[275],"printable":true,"separator":false,"breaking":false,"modifier":false},"113":{"id":"q","keyCode":"KeyQ","title":"Lowercase q","alias":[276],"printable":true,"separator":false,"breaking":false,"modifier":false},"114":{"id":"r","keyCode":"KeyR","title":"Lowercase r","alias":[277],"printable":true,"separator":false,"breaking":false,"modifier":false},"115":{"id":"s","keyCode":"KeyS","title":"Lowercase s","alias":[278],"printable":true,"separator":false,"breaking":false,"modifier":false},"116":{"id":"t","keyCode":"KeyT","title":"Lowercase t","alias":[279],"printable":true,"separator":false,"breaking":false,"modifier":false},"117":{"id":"u","keyCode":"KeyU","title":"Lowercase u","alias":[280],"printable":true,"separator":false,"breaking":false,"modifier":false},"118":{"id":"v","keyCode":"KeyV","title":"Lowercase v","alias":[281],"printable":true,"separator":false,"breaking":false,"modifier":false},"119":{"id":"w","KeyCode":"KeyW","title":"Lowercase w","alias":[282],"printable":true,"separator":false,"breaking":false,"modifier":false},"120":{"id":"x","keyCode":"KeyX","title":"Lowercase x","alias":[283],"printable":true,"separator":false,"breaking":false,"modifier":false},"121":{"id":"y","keyCode":"KeyY","title":"Lowercase y","alias":[284],"printable":true,"separator":false,"breaking":false,"modifier":false},"122":{"id":"z","keyCode":"KeyZ","title":"Lowercase z","alias":[285],"printable":true,"separator":false,"breaking":false,"modifier":false}}},{"name":"ASCII Macros","actions":{"33":{"id":"!","name":"EXCLAMATION","title":"Exclamation Point","separator":true,"printable":true,"breaking":false,"modifier":false},"34":{"id":"\"","name":"DOUBLE_QUOTE","title":"Double Quote","separator":true,"printable":true,"breaking":false,"modifier":false},"35":{"id":"#","name":"HASH","title":"Hash Symbol","separator":true,"printable":true,"breaking":false,"modifier":false},"36":{"id":"$","name":"DOLLAR","title":"Dollar Sign","separator":true,"printable":true,"breaking":false,"modifier":false},"37":{"id":"%","name":"PERCENT","title":"Percent","separator":true,"printable":true,"breaking":false,"modifier":false},"38":{"id":"&","name":"AMPERSAND","title":"Ampersand","separator":true,"printable":true,"breaking":false,"modifier":false},"40":{"id":"(","name":"LEFT_PARENTHESIS","title":"Opening Parenthesis","separator":true,"printable":true,"breaking":false,"modifier":false},"41":{"id":")","name":"RIGHT_PARENTHESIS","title":"Closing Parenthesis","separator":true,"printable":true,"breaking":false,"modifier":false},"42":{"id":"*","title":"Asterisk","separator":true,"printable":true,"breaking":false,"modifier":false},"43":{"id":"+","title":"Plus","separator":true,"printable":true,"breaking":false,"modifier":false},"58":{"id":":","title":"Colon","separator":true,"printable":true,"breaking":false,"modifier":false},"60":{"id":"<","title":"Less Than","separator":true,"printable":true,"breaking":false,"modifier":false},"62":{"id":">","title":"Greater Than","separator":true,"printable":true,"breaking":false,"modifier":false},"63":{"id":"?","name":"QUESTION","title":"Question Mark","printable":true,"separator":false,"breaking":false,"modifier":false},"64":{"id":"@","name":"AT","title":"At Symbol","separator":true,"printable":true,"breaking":false,"modifier":false},"65":{"id":"A","title":"Uppercase A","printable":true,"separator":false,"breaking":false,"modifier":false},"66":{"id":"B","title":"Uppercase B","printable":true,"separator":false,"breaking":false,"modifier":false},"67":{"id":"C","title":"Uppercase C","printable":true,"separator":false,"breaking":false,"modifier":false},"68":{"id":"D","title":"Uppercase D","printable":true,"separator":false,"breaking":false,"modifier":false},"69":{"id":"E","title":"Uppercase E","printable":true,"separator":false,"breaking":false,"modifier":false},"70":{"id":"F","title":"Uppercase F","printable":true,"separator":false,"breaking":false,"modifier":false},"71":{"id":"G","title":"Uppercase G","printable":true,"separator":false,"breaking":false,"modifier":false},"72":{"id":"H","title":"Uppercase H","printable":true,"separator":false,"breaking":false,"modifier":false},"73":{"id":"I","title":"Uppercase I","printable":true,"separator":false,"breaking":false,"modifier":false},"74":{"id":"J","title":"Uppercase J","printable":true,"separator":false,"breaking":false,"modifier":false},"75":{"id":"K","title":"Uppercase K","printable":true,"separator":false,"breaking":false,"modifier":false},"76":{"id":"L","title":"Uppercase L","printable":true,"separator":false,"breaking":false,"modifier":false},"77":{"id":"M","title":"Uppercase M","printable":true,"separator":false,"breaking":false,"modifier":false},"78":{"id":"N","title":"Uppercase N","printable":true,"separator":false,"breaking":false,"modifier":false},"79":{"id":"O","title":"Uppercase O","printable":true,"separator":false,"breaking":false,"modifier":false},"80":{"id":"P","title":"Uppercase P","printable":true,"separator":false,"breaking":false,"modifier":false},"81":{"id":"Q","title":"Uppercase Q","printable":true,"separator":false,"breaking":false,"modifier":false},"82":{"id":"R","title":"Uppercase R","printable":true,"separator":false,"breaking":false,"modifier":false},"83":{"id":"S","title":"Uppercase S","printable":true,"separator":false,"breaking":false,"modifier":false},"84":{"id":"T","title":"Uppercase T","printable":true,"separator":false,"breaking":false,"modifier":false},"85":{"id":"U","title":"Uppercase U","printable":true,"separator":false,"breaking":false,"modifier":false},"86":{"id":"V","title":"Uppercase V","printable":true,"separator":false,"breaking":false,"modifier":false},"87":{"id":"W","title":"Uppercase W","printable":true,"separator":false,"breaking":false,"modifier":false},"88":{"id":"X","title":"Uppercase X","printable":true,"separator":false,"breaking":false,"modifier":false},"89":{"id":"Y","title":"Uppercase Y","printable":true,"separator":false,"breaking":false,"modifier":false},"90":{"id":"Z","title":"Uppercase Z","printable":true,"separator":false,"breaking":false,"modifier":false},"94":{"id":"^","title":"Caret","separator":true,"printable":true,"breaking":false,"modifier":false},"95":{"id":"_","title":"Underscore","separator":true,"printable":true,"breaking":false,"modifier":false},"123":{"id":"{","name":"LEFT_BRACE","title":"Left Curly Brace","separator":true,"printable":true,"breaking":false,"modifier":false},"124":{"id":"|","title":"Pipe","separator":true,"printable":true,"breaking":false,"modifier":false},"797":{"id":"| (ISO)","name":"ISO_PIPE","separator":true,"description":"On ISO keyboards (L-shaped ENTER key) this extra key is found to the right of the left shift key.","printable":true,"breaking":false,"modifier":false},"125":{"id":"}","name":"RIGHT_BRACE","title":"Right Curly Brace","separator":true,"printable":true,"breaking":false,"modifier":false},"126":{"id":"~","title":"Tilde","separator":true,"printable":true,"breaking":false,"modifier":false}}},{"name":"Media Keys","actions":{"800":{"name":"CONSUMER_CONTROL_POWER","title":"Power","icon":"power_settings_circle","printable":false,"separator":true,"breaking":false,"modifier":false},"801":{"name":"CONSUMER_CONTROL_RESET","title":"Reset","icon":"device_reset","printable":false,"separator":true,"breaking":false,"modifier":false},"802":{"name":"CONSUMER_CONTROL_SLEEP","title":"Sleep","icon":"bedtime","printable":false,"separator":true,"breaking":false,"modifier":false},"803":{"name":"CONSUMER_CONTROL_BRIGHTNESS_INCREMENT","title":"Brightness Up","icon":"brightness_high","printable":false,"separator":true,"breaking":false,"modifier":false},"804":{"name":"CONSUMER_CONTROL_BRIGHTNESS_DECREMENT","title":"Brightness Down","icon":"brightness_low","printable":false,"separator":true,"breaking":false,"modifier":false},"805":{"name":"CONSUMER_CONTROL_WIRELESS_RADIO_CONTROLS","title":"Wireless Radio Controls","icon":"wifi","printable":false,"separator":true,"breaking":false,"modifier":false},"806":{"name":"CONSUMER_CONTROL_WIRELESS_RADIO_BUTTONS","title":"Wireless Radio Buttons","icon":"wifi","printable":false,"separator":true,"breaking":false,"modifier":false},"807":{"name":"CONSUMER_CONTROL_WIRELESS_RADIO_LED","title":"Wireless Radio LED","icon":"wifi","printable":false,"separator":true,"breaking":false,"modifier":false},"808":{"name":"CONSUMER_CONTROL_WIRELESS_RADIO_SLIDER_SWITCH","title":"Wireless Radio Slider","icon":"wifi","printable":false,"separator":true,"breaking":false,"modifier":false},"809":{"name":"CONSUMER_CONTROL_PLAY_PAUSE","title":"Play/Pause","icon":"play_pause","printable":false,"separator":true,"breaking":false,"modifier":false},"810":{"name":"CONSUMER_CONTROL_SCAN_NEXT","title":"Next Track","icon":"skip_next","printable":false,"separator":true,"breaking":false,"modifier":false},"811":{"name":"CONSUMER_CONTROL_SCAN_PREVIOUS","title":"Previous Track","icon":"skip_previous","printable":false,"separator":true,"breaking":false,"modifier":false},"812":{"name":"CONSUMER_CONTROL_STOP","title":"Stop","icon":"stop","printable":false,"separator":true,"breaking":false,"modifier":false},"813":{"name":"CONSUMER_CONTROL_VOLUME","title":"Volume","icon":"ring_volume","printable":false,"separator":true,"breaking":false,"modifier":false},"814":{"name":"CONSUMER_CONTROL_MUTE","title":"Mute","icon":"no_sound","printable":false,"separator":true,"breaking":false,"modifier":false},"815":{"name":"CONSUMER_CONTROL_BASS","title":"Bass","icon":"graphic_eq","printable":false,"separator":true,"breaking":false,"modifier":false},"816":{"name":"CONSUMER_CONTROL_TREBLE","title":"Treble","icon":"sound_detection_loud_sound","printable":false,"separator":true,"breaking":false,"modifier":false},"817":{"name":"CONSUMER_CONTROL_BASS_BOOST","title":"Bass Boost","icon":"sound_detection_loud_sound","printable":false,"separator":true,"breaking":false,"modifier":false},"818":{"name":"CONSUMER_CONTROL_VOLUME_INCREMENT","title":"Volume Up","icon":"volume_up","printable":false,"separator":true,"breaking":false,"modifier":false},"819":{"name":"CONSUMER_CONTROL_VOLUME_DECREMENT","title":"Volume Down","icon":"volume_down","printable":false,"separator":true,"breaking":false,"modifier":false},"820":{"name":"CONSUMER_CONTROL_BASS_INCREMENT","title":"Bass Up","icon":"volume_up","printable":false,"separator":true,"breaking":false,"modifier":false},"821":{"name":"CONSUMER_CONTROL_BASS_DECREMENT","title":"Bass Down","icon":"volume_down","printable":false,"separator":true,"breaking":false,"modifier":false},"822":{"name":"CONSUMER_CONTROL_TREBLE_INCREMENT","title":"Treble Up","icon":"volume_up","printable":false,"separator":true,"breaking":false,"modifier":false},"823":{"name":"CONSUMER_CONTROL_TREBLE_DECREMENT","title":"Treble Down","icon":"volume_down","printable":false,"separator":true,"breaking":false,"modifier":false},"824":{"name":"CONSUMER_CONTROL_CONFIGURATION","title":"Configuration","icon":"settings","printable":false,"separator":true,"breaking":false,"modifier":false},"825":{"name":"CONSUMER_CONTROL_EMAIL_READER","title":"Email Reader","icon":"mail","printable":false,"separator":true,"breaking":false,"modifier":false},"826":{"name":"CONSUMER_CONTROL_CALCULATOR","title":"Calculator","icon":"calculate","printable":false,"separator":true,"breaking":false,"modifier":false},"827":{"name":"CONSUMER_CONTROL_LOCAL_BROWSER","title":"Browser","icon":"open_in_browser","printable":false,"separator":true,"breaking":false,"modifier":false},"828":{"name":"CONSUMER_CONTROL_SEARCH","title":"Search","icon":"search","printable":false,"separator":true,"breaking":false,"modifier":false},"829":{"name":"CONSUMER_CONTROL_HOME","title":"Home","icon":"home","printable":false,"separator":true,"breaking":false,"modifier":false},"830":{"name":"CONSUMER_CONTROL_BACK","title":"Back","icon":"chevron_backward","printable":false,"separator":true,"breaking":false,"modifier":false},"831":{"name":"CONSUMER_CONTROL_FORWARD","title":"Forward","icon":"chevron_forward","printable":false,"separator":true,"breaking":false,"modifier":false},"832":{"name":"CONSUMER_CONTROL_BR_STOP","title":"Browser Stop","icon":"stop_circle","printable":false,"separator":true,"breaking":false,"modifier":false},"833":{"name":"CONSUMER_CONTROL_REFRESH","title":"Refresh","icon":"refresh","printable":false,"separator":true,"breaking":false,"modifier":false},"834":{"name":"CONSUMER_CONTROL_BOOKMARKS","title":"Bookmarks","icon":"bookmark","printable":false,"separator":true,"breaking":false,"modifier":false},"835":{"name":"CONSUMER_CONTROL_PAN","title":"Horizontal Scroll","icon":"drag_pan","printable":false,"separator":true,"breaking":false,"modifier":false}}},{"name":"Keypad","actions":{"327":{"id":"SCRLK","name":"SCROLL_LOCK","keyCode":"ScrollLock","title":"Keyboard Scroll Lock","printable":false,"separator":true,"breaking":false,"modifier":false},"339":{"id":"NUMLOCK","keyCode":"NumLock","title":"Keyboard Num Lock and Clear","printable":false,"separator":true,"breaking":false,"modifier":false},"344":{"id":"KP_ENTER","keyCode":"NumpadEnter","title":"Keypad Enter","printable":true,"separator":false,"breaking":false,"modifier":false},"345":{"id":"KP_1","keyCode":"Numpad1","title":"Keypad 1 and End","printable":true,"separator":false,"breaking":false,"modifier":false},"346":{"id":"KP_2","keyCode":"Numpad2","title":"Keypad 2 and Down Arrow","printable":true,"separator":false,"breaking":false,"modifier":false},"347":{"id":"KP_3","keyCode":"Numpad3","title":"Keypad 3 and Page Down","printable":true,"separator":false,"breaking":false,"modifier":false},"348":{"id":"KP_4","keyCode":"Numpad4","title":"Keypad 4 and Left Arrow","printable":true,"separator":false,"breaking":false,"modifier":false},"349":{"id":"KP_5","keyCode":"Numpad5","title":"Keypad 5","printable":true,"separator":false,"breaking":false,"modifier":false},"350":{"id":"KP_6","keyCode":"Numpad6","title":"Keypad 6 and Rigth Arrow","printable":true,"separator":false,"breaking":false,"modifier":false},"351":{"id":"KP_7","keyCode":"Numpad7","title":"Keypad 7 and Home","printable":true,"separator":false,"breaking":false,"modifier":false},"352":{"id":"KP_8","keyCode":"Numpad8","title":"Keypad 8 and Up Arrow","printable":true,"separator":false,"breaking":false,"modifier":false},"353":{"id":"KP_9","keyCode":"Numpad9","title":"Keypad 9 and Page Up","printable":true,"separator":false,"breaking":false,"modifier":false},"354":{"id":"KP_0","keyCode":"Numpad0","title":"Keypad 0 and Insert","printable":true,"separator":false,"breaking":false,"modifier":false},"340":{"id":"KP_SLASH","keyCode":"NumpadDivide","title":"Keypad /","printable":true,"separator":false,"breaking":false,"modifier":false},"341":{"id":"KP_ASTER","keyCode":"NumpadStar","title":"Keypad *","printable":true,"separator":false,"breaking":false,"modifier":false},"342":{"id":"KP_MINUS","keyCode":"NumpadSubtract","title":"Keypad -","printable":true,"separator":false,"breaking":false,"modifier":false},"343":{"id":"KP_PLUS","keyCode":"NumpadAdd","title":"Keypad +","printable":true,"separator":false,"breaking":false,"modifier":false},"355":{"id":"KP_DOT","keyCode":"NumpadDecimal","title":"Keypad . and Delete","printable":true,"separator":false,"breaking":false,"modifier":false},"359":{"id":"KP_EQUAL","keyCode":"NumpadEqual","title":"Keypad =","description":"Only officially supported by Mac","printable":true,"separator":false,"breaking":false,"modifier":false}}},{"name":"Uncommon","description":"Internal and rarely used actions.\n","actions":{"0":{"id":"NO_ACTION","name":"NULL","display":"No Action","breaking":true,"printable":false,"separator":true,"modifier":false},"528":{"id":"RESTART","title":"Restart Device","icon":"restart_alt","breaking":true,"printable":false,"separator":true,"modifier":false},"530":{"id":"BOOT","title":"Reboot to Bootloader","icon":"rule_settings","breaking":true,"printable":false,"separator":true,"modifier":false},"537":{"id":"UNDO_CHORD","title":"Undo last chord","icon":"text_select_move_back_word","printable":false,"separator":true,"breaking":false,"modifier":false},"257":{"id":"KSC_01","title":"Keyboard Error Roll Over","breaking":true,"printable":false,"separator":true,"modifier":false},"258":{"id":"KSC_02","title":"Keyboard POST Fail","breaking":true,"printable":false,"separator":true,"modifier":false},"259":{"id":"KSC_03","title":"Keyboard Error Undefined","breaking":true,"printable":false,"separator":true,"modifier":false},"357":{"id":"COMPOSE","icon":"menu","title":"Menu","printable":false,"separator":true,"breaking":false,"modifier":false},"358":{"id":"POWER","keyCode":"Power","title":"Keyboard Power","description":"Only officially supported by Mac and Unix","breaking":true,"printable":false,"separator":true,"modifier":false},"326":{"id":"PRTSCN","name":"PRINT_SCREEN","keyCode":"PrintScreen","title":"Keyboard Print Screen","icon":"screenshot_monitor","printable":false,"separator":true,"breaking":false,"modifier":false},"328":{"id":"PAUSE","keyCode":"Pause","title":"Keyboard Pause","printable":false,"separator":true,"breaking":false,"modifier":false},"329":{"id":"INSERT","keyCode":"Insert","title":"Keyboard Insert","breaking":true,"printable":false,"separator":true,"modifier":false},"260":{"id":"KEY_A","printable":true,"separator":false,"breaking":false,"modifier":false},"261":{"id":"KEY_B","printable":true,"separator":false,"breaking":false,"modifier":false},"262":{"id":"KEY_C","printable":true,"separator":false,"breaking":false,"modifier":false},"263":{"id":"KEY_D","printable":true,"separator":false,"breaking":false,"modifier":false},"264":{"id":"KEY_E","printable":true,"separator":false,"breaking":false,"modifier":false},"265":{"id":"KEY_F","printable":true,"separator":false,"breaking":false,"modifier":false},"266":{"id":"KEY_G","printable":true,"separator":false,"breaking":false,"modifier":false},"267":{"id":"KEY_H","printable":true,"separator":false,"breaking":false,"modifier":false},"268":{"id":"KEY_I","printable":true,"separator":false,"breaking":false,"modifier":false},"269":{"id":"KEY_J","printable":true,"separator":false,"breaking":false,"modifier":false},"270":{"id":"KEY_K","printable":true,"separator":false,"breaking":false,"modifier":false},"271":{"id":"KEY_L","printable":true,"separator":false,"breaking":false,"modifier":false},"272":{"id":"KEY_M","printable":true,"separator":false,"breaking":false,"modifier":false},"273":{"id":"KEY_N","printable":true,"separator":false,"breaking":false,"modifier":false},"274":{"id":"KEY_O","printable":true,"separator":false,"breaking":false,"modifier":false},"275":{"id":"KEY_P","printable":true,"separator":false,"breaking":false,"modifier":false},"276":{"id":"KEY_Q","printable":true,"separator":false,"breaking":false,"modifier":false},"277":{"id":"KEY_R","printable":true,"separator":false,"breaking":false,"modifier":false},"278":{"id":"KEY_S","printable":true,"separator":false,"breaking":false,"modifier":false},"279":{"id":"KEY_T","printable":true,"separator":false,"breaking":false,"modifier":false},"280":{"id":"KEY_U","printable":true,"separator":false,"breaking":false,"modifier":false},"281":{"id":"KEY_V","printable":true,"separator":false,"breaking":false,"modifier":false},"282":{"id":"KEY_W","printable":true,"separator":false,"breaking":false,"modifier":false},"283":{"id":"KEY_X","printable":true,"separator":false,"breaking":false,"modifier":false},"284":{"id":"KEY_Y","printable":true,"separator":false,"breaking":false,"modifier":false},"285":{"id":"KEY_Z","printable":true,"separator":false,"breaking":false,"modifier":false},"286":{"id":"KEY_1","printable":true,"separator":false,"breaking":false,"modifier":false},"287":{"id":"KEY_2","printable":true,"separator":false,"breaking":false,"modifier":false},"288":{"id":"KEY_3","printable":true,"separator":false,"breaking":false,"modifier":false},"289":{"id":"KEY_4","printable":true,"separator":false,"breaking":false,"modifier":false},"290":{"id":"KEY_5","printable":true,"separator":false,"breaking":false,"modifier":false},"291":{"id":"KEY_6","printable":true,"separator":false,"breaking":false,"modifier":false},"292":{"id":"KEY_7","printable":true,"separator":false,"breaking":false,"modifier":false},"293":{"id":"KEY_8","printable":true,"separator":false,"breaking":false,"modifier":false},"294":{"id":"KEY_9","printable":true,"separator":false,"breaking":false,"modifier":false},"295":{"id":"KEY_0","printable":true,"separator":false,"breaking":false,"modifier":false},"300":{"id":"KEY_SPACE","printable":true,"separator":false,"breaking":false,"modifier":false},"301":{"id":"KSC_MINUS","printable":true,"separator":false,"breaking":false,"modifier":false},"302":{"id":"KSC_EQUAL","printable":true,"separator":false,"breaking":false,"modifier":false},"303":{"id":"KSC_LEFT_BRACKET","printable":true,"separator":false,"breaking":false,"modifier":false},"304":{"id":"KSC_RIGHT_BRACKET","printable":true,"separator":false,"breaking":false,"modifier":false},"305":{"id":"KSC_BACKSLASH","printable":true,"separator":false,"breaking":false,"modifier":false},"306":{"id":"# (ISO)","title":"ISO Hashpound","description":"On ISO keyboards (L-shaped ENTER key) this key is found to the bottom left of the ENTER key.\nIt is effectively the same as the ANSI Backslash key.\n","separator":true,"printable":true,"breaking":false,"modifier":false},"307":{"id":"KSC_SEMICOLON","printable":true,"separator":false,"breaking":false,"modifier":false},"308":{"id":"KSC_QUOTE","printable":true,"separator":false,"breaking":false,"modifier":false},"309":{"id":"KSC_BACKTICK","printable":true,"separator":false,"breaking":false,"modifier":false},"310":{"id":"KSC_COMMA","printable":true,"separator":false,"breaking":false,"modifier":false},"311":{"id":"KSC_PERIOD","printable":true,"separator":false,"breaking":false,"modifier":false},"312":{"id":"KSC_SLASH","printable":true,"separator":false,"breaking":false,"modifier":false},"332":{"id":"KSC_DEL","printable":true,"separator":false,"breaking":false,"modifier":false},"372":{"id":"KSC_74","printable":false,"separator":true,"breaking":false,"modifier":false},"373":{"id":"KSC_75","printable":false,"separator":true,"breaking":false,"modifier":false},"374":{"id":"KSC_76","printable":false,"separator":true,"breaking":false,"modifier":false},"375":{"id":"KSC_77","printable":false,"separator":true,"breaking":false,"modifier":false},"376":{"id":"KSC_78","printable":false,"separator":true,"breaking":false,"modifier":false},"377":{"id":"KSC_79","printable":false,"separator":true,"breaking":false,"modifier":false},"378":{"id":"KSC_7A","printable":false,"separator":true,"breaking":false,"modifier":false},"379":{"id":"KSC_7B","printable":false,"separator":true,"breaking":false,"modifier":false},"380":{"id":"KSC_7C","printable":false,"separator":true,"breaking":false,"modifier":false},"381":{"id":"KSC_7D","printable":false,"separator":true,"breaking":false,"modifier":false},"382":{"id":"KSC_7E","printable":false,"separator":true,"breaking":false,"modifier":false},"383":{"id":"KSC_7F","printable":false,"separator":true,"breaking":false,"modifier":false},"384":{"id":"KSC_80","printable":false,"separator":true,"breaking":false,"modifier":false},"385":{"id":"KSC_81","printable":false,"separator":true,"breaking":false,"modifier":false},"386":{"id":"KSC_82","printable":false,"separator":true,"breaking":false,"modifier":false},"387":{"id":"KSC_83","printable":false,"separator":true,"breaking":false,"modifier":false},"388":{"id":"KSC_84","printable":false,"separator":true,"breaking":false,"modifier":false},"389":{"id":"KSC_85","printable":false,"separator":true,"breaking":false,"modifier":false},"390":{"id":"KSC_86","printable":false,"separator":true,"breaking":false,"modifier":false},"391":{"id":"KSC_87","printable":false,"separator":true,"breaking":false,"modifier":false},"392":{"id":"KSC_88","printable":false,"separator":true,"breaking":false,"modifier":false},"393":{"id":"KSC_89","printable":false,"separator":true,"breaking":false,"modifier":false},"394":{"id":"KSC_8A","printable":false,"separator":true,"breaking":false,"modifier":false},"395":{"id":"KSC_8B","printable":false,"separator":true,"breaking":false,"modifier":false},"396":{"id":"KSC_8C","printable":false,"separator":true,"breaking":false,"modifier":false},"397":{"id":"KSC_8D","printable":false,"separator":true,"breaking":false,"modifier":false},"398":{"id":"KSC_8E","printable":false,"separator":true,"breaking":false,"modifier":false},"399":{"id":"KSC_8F","printable":false,"separator":true,"breaking":false,"modifier":false},"400":{"id":"KSC_90","printable":false,"separator":true,"breaking":false,"modifier":false},"401":{"id":"KSC_91","printable":false,"separator":true,"breaking":false,"modifier":false},"402":{"id":"KSC_92","printable":false,"separator":true,"breaking":false,"modifier":false},"403":{"id":"KSC_93","printable":false,"separator":true,"breaking":false,"modifier":false},"404":{"id":"KSC_94","printable":false,"separator":true,"breaking":false,"modifier":false},"405":{"id":"KSC_95","printable":false,"separator":true,"breaking":false,"modifier":false},"406":{"id":"KSC_96","printable":false,"separator":true,"breaking":false,"modifier":false},"407":{"id":"KSC_97","printable":false,"separator":true,"breaking":false,"modifier":false},"408":{"id":"KSC_98","printable":false,"separator":true,"breaking":false,"modifier":false},"409":{"id":"KSC_99","printable":false,"separator":true,"breaking":false,"modifier":false},"410":{"id":"KSC_9A","printable":false,"separator":true,"breaking":false,"modifier":false},"411":{"id":"KSC_9B","printable":false,"separator":true,"breaking":false,"modifier":false},"412":{"id":"KSC_9C","printable":false,"separator":true,"breaking":false,"modifier":false},"413":{"id":"KSC_9D","printable":false,"separator":true,"breaking":false,"modifier":false},"414":{"id":"KSC_9E","printable":false,"separator":true,"breaking":false,"modifier":false},"415":{"id":"KSC_9F","printable":false,"separator":true,"breaking":false,"modifier":false},"416":{"id":"KSC_A0","printable":false,"separator":true,"breaking":false,"modifier":false},"417":{"id":"KSC_A1","printable":false,"separator":true,"breaking":false,"modifier":false},"418":{"id":"KSC_A2","printable":false,"separator":true,"breaking":false,"modifier":false},"419":{"id":"KSC_A3","printable":false,"separator":true,"breaking":false,"modifier":false},"420":{"id":"KSC_A4","printable":false,"separator":true,"breaking":false,"modifier":false},"421":{"id":"KSC_A5","printable":false,"separator":true,"breaking":false,"modifier":false},"422":{"id":"KSC_A6","printable":false,"separator":true,"breaking":false,"modifier":false},"423":{"id":"KSC_A7","printable":false,"separator":true,"breaking":false,"modifier":false},"424":{"id":"KSC_A8","printable":false,"separator":true,"breaking":false,"modifier":false},"425":{"id":"KSC_A9","printable":false,"separator":true,"breaking":false,"modifier":false},"426":{"id":"KSC_AA","printable":false,"separator":true,"breaking":false,"modifier":false},"427":{"id":"KSC_AB","printable":false,"separator":true,"breaking":false,"modifier":false},"428":{"id":"KSC_AC","printable":false,"separator":true,"breaking":false,"modifier":false},"429":{"id":"KSC_AD","printable":false,"separator":true,"breaking":false,"modifier":false},"430":{"id":"KSC_AE","printable":false,"separator":true,"breaking":false,"modifier":false},"431":{"id":"KSC_AF","printable":false,"separator":true,"breaking":false,"modifier":false},"432":{"id":"KSC_B0","printable":false,"separator":true,"breaking":false,"modifier":false},"433":{"id":"KSC_B1","printable":false,"separator":true,"breaking":false,"modifier":false},"434":{"id":"KSC_B2","printable":false,"separator":true,"breaking":false,"modifier":false},"435":{"id":"KSC_B3","printable":true,"separator":false,"breaking":false,"modifier":false},"436":{"id":"KSC_B4","printable":false,"separator":true,"breaking":false,"modifier":false},"437":{"id":"KSC_B5","printable":false,"separator":true,"breaking":false,"modifier":false},"438":{"id":"KSC_B6","printable":false,"separator":true,"breaking":false,"modifier":false},"439":{"id":"KSC_B7","printable":false,"separator":true,"breaking":false,"modifier":false},"440":{"id":"KSC_B8","printable":false,"separator":true,"breaking":false,"modifier":false},"441":{"id":"KSC_B9","printable":false,"separator":true,"breaking":false,"modifier":false},"442":{"id":"KSC_BA","printable":false,"separator":true,"breaking":false,"modifier":false},"443":{"id":"KSC_BB","printable":false,"separator":true,"breaking":false,"modifier":false},"444":{"id":"KSC_BC","printable":false,"separator":true,"breaking":false,"modifier":false},"445":{"id":"KSC_BD","printable":false,"separator":true,"breaking":false,"modifier":false},"446":{"id":"KSC_BE","printable":false,"separator":true,"breaking":false,"modifier":false},"447":{"id":"KSC_BF","printable":false,"separator":true,"breaking":false,"modifier":false},"448":{"id":"KSC_C0","printable":false,"separator":true,"breaking":false,"modifier":false},"449":{"id":"KSC_C1","printable":false,"separator":true,"breaking":false,"modifier":false},"450":{"id":"KSC_C2","printable":false,"separator":true,"breaking":false,"modifier":false},"451":{"id":"KSC_C3","printable":false,"separator":true,"breaking":false,"modifier":false},"452":{"id":"KSC_C4","printable":false,"separator":true,"breaking":false,"modifier":false},"453":{"id":"KSC_C5","printable":false,"separator":true,"breaking":false,"modifier":false},"454":{"id":"KSC_C6","printable":false,"separator":true,"breaking":false,"modifier":false},"455":{"id":"KSC_C7","printable":false,"separator":true,"breaking":false,"modifier":false},"456":{"id":"KSC_C8","printable":false,"separator":true,"breaking":false,"modifier":false},"457":{"id":"KSC_C9","printable":false,"separator":true,"breaking":false,"modifier":false},"458":{"id":"KSC_CA","printable":false,"separator":true,"breaking":false,"modifier":false},"459":{"id":"KSC_CB","printable":false,"separator":true,"breaking":false,"modifier":false},"460":{"id":"KSC_CC","printable":false,"separator":true,"breaking":false,"modifier":false},"461":{"id":"KSC_CD","printable":false,"separator":true,"breaking":false,"modifier":false},"462":{"id":"KSC_CE","printable":false,"separator":true,"breaking":false,"modifier":false},"463":{"id":"KSC_CF","printable":false,"separator":true,"breaking":false,"modifier":false},"464":{"id":"KSC_D0","printable":false,"separator":true,"breaking":false,"modifier":false},"465":{"id":"KSC_D1","printable":false,"separator":true,"breaking":false,"modifier":false},"466":{"id":"KSC_D2","printable":false,"separator":true,"breaking":false,"modifier":false},"467":{"id":"KSC_D3","printable":false,"separator":true,"breaking":false,"modifier":false},"468":{"id":"KSC_D4","printable":false,"separator":true,"breaking":false,"modifier":false},"469":{"id":"KSC_D5","printable":false,"separator":true,"breaking":false,"modifier":false},"470":{"id":"KSC_D6","printable":false,"separator":true,"breaking":false,"modifier":false},"471":{"id":"KSC_D7","printable":false,"separator":true,"breaking":false,"modifier":false},"472":{"id":"KSC_D8","printable":false,"separator":true,"breaking":false,"modifier":false},"473":{"id":"KSC_D9","printable":false,"separator":true,"breaking":false,"modifier":false},"474":{"id":"KSC_DA","printable":false,"separator":true,"breaking":false,"modifier":false},"475":{"id":"KSC_DB","printable":false,"separator":true,"breaking":false,"modifier":false},"476":{"id":"KSC_DC","printable":false,"separator":true,"breaking":false,"modifier":false},"477":{"id":"KSC_DD","printable":false,"separator":true,"breaking":false,"modifier":false},"478":{"id":"KSC_DE","printable":false,"separator":true,"breaking":false,"modifier":false},"479":{"id":"KSC_DF","printable":false,"separator":true,"breaking":false,"modifier":false},"480":{"id":"KSC_E0","printable":false,"separator":true,"breaking":false,"modifier":false},"481":{"id":"KSC_E1","printable":false,"separator":true,"breaking":false,"modifier":false},"482":{"id":"KSC_E2","printable":false,"separator":true,"breaking":false,"modifier":false},"483":{"id":"KSC_E3","printable":false,"separator":true,"breaking":false,"modifier":false},"484":{"id":"KSC_E4","printable":false,"separator":true,"breaking":false,"modifier":false},"485":{"id":"KSC_E5","printable":false,"separator":true,"breaking":false,"modifier":false},"486":{"id":"KSC_E6","printable":false,"separator":true,"breaking":false,"modifier":false},"487":{"id":"KSC_E7","printable":false,"separator":true,"breaking":false,"modifier":false},"488":{"id":"KSC_E8","printable":false,"separator":true,"breaking":false,"modifier":false},"489":{"id":"KSC_E9","printable":false,"separator":true,"breaking":false,"modifier":false},"490":{"id":"KSC_EA","printable":false,"separator":true,"breaking":false,"modifier":false},"491":{"id":"KSC_EB","printable":false,"separator":true,"breaking":false,"modifier":false},"492":{"id":"KSC_EC","printable":false,"separator":true,"breaking":false,"modifier":false},"493":{"id":"KSC_ED","printable":false,"separator":true,"breaking":false,"modifier":false},"494":{"id":"KSC_EE","printable":false,"separator":true,"breaking":false,"modifier":false},"495":{"id":"KSC_EF","printable":false,"separator":true,"breaking":false,"modifier":false},"496":{"id":"KSC_F0","printable":false,"separator":true,"breaking":false,"modifier":false},"497":{"id":"KSC_F1","printable":false,"separator":true,"breaking":false,"modifier":false},"498":{"id":"KSC_F2","printable":false,"separator":true,"breaking":false,"modifier":false},"499":{"id":"KSC_F3","printable":false,"separator":true,"breaking":false,"modifier":false},"500":{"id":"KSC_F4","printable":false,"separator":true,"breaking":false,"modifier":false},"501":{"id":"KSC_F5","printable":false,"separator":true,"breaking":false,"modifier":false},"502":{"id":"KSC_F6","printable":false,"separator":true,"breaking":false,"modifier":false},"503":{"id":"KSC_F7","printable":false,"separator":true,"breaking":false,"modifier":false},"504":{"id":"KSC_F8","printable":false,"separator":true,"breaking":false,"modifier":false},"505":{"id":"KSC_F9","printable":false,"separator":true,"breaking":false,"modifier":false},"506":{"id":"KSC_FA","printable":false,"separator":true,"breaking":false,"modifier":false},"507":{"id":"KSC_FB","printable":false,"separator":true,"breaking":false,"modifier":false},"508":{"id":"KSC_FC","printable":false,"separator":true,"breaking":false,"modifier":false},"509":{"id":"KSC_FD","printable":false,"separator":true,"breaking":false,"modifier":false},"510":{"id":"KSC_FE","printable":false,"separator":true,"breaking":false,"modifier":false},"511":{"id":"KSC_FF","printable":false,"separator":true,"breaking":false,"modifier":false},"1023":{"id":"ACTION_MAX","name":"LAST_ONE","printable":false,"breaking":true,"separator":true,"modifier":false}}}]